Workbook

Sheet Comparison
A1: Combined Data | B1: POST /quotes | C1: Mapped | D1: PUT /quotes | E1: Mapped | F1: POST /transfers | G1: Mapped | H1: PUT /transfers | I1: Mapped | J1: Definition
A2: Description | B2: Request that a Peer FSP create a new quote for performing a transaction. | D2: Callback to inform a Peer FSP about a previously- requested quote. | F2: Request a Peer FSP to perform the transfer of funds related to a transaction. | H2: Callback to inform a Peer FSP about a previously-performed transfer. | J2: Primary | K2: Secondary
A3: quoteId | B3: quoteId | C3: Yes | D3: quoteId (from URI) | J3: Common ID between the FSPs for the quote object, decided by the Payer FSP. The ID should be reused for resends of the same quote for a transaction. A new ID should be generated for each new quote for a transaction.
A4: transactionId | B4: transactionId | C4: Yes | J4: Common ID (decided by the Payer FSP) between the FSPs for the future transaction object. The actual transaction will be created as part of a successful transfer process. The ID should be reused for resends of the same quote for a transaction. A new ID should be generated for each new quote for a transaction.
A5: transferId | C5: No | F5: transferId | G5: Yes | H5: transferId (from URI) | I5: Yes | J5: The common ID between the FSPs and the optional Switch for the transfer object, decided by the Payer FSP. The ID should be reused for resends of the same transfer. A new ID should be generated for each new transfer.
A6: transactionRequestId | B6: transactionRequestId | C6: No | J6: Identifies an optional previously-sent transaction request.
A7: payee | B7: payee | C7: N/A | J7: Information about the Payee in the proposed financial transaction.
A8: payee.partyIdInfo | B8: payee.partyIdInfo | C8: N/A | J8: Party Id type, id, sub ID or type, and FSP Id.
A9: payee.partyIdInfo.partyIdType | B9: payee.partyIdInfo.partyIdType | C9: Yes | J9: The type of the identifier.
A10: payee.partyIdInfo.partyIdentifier | B10: payee.partyIdInfo.partyIdentifier | C10: Yes | J10: An identifier for the Party.
A11: payee.partyIdInfo.partySubIdOrType | B11: payee.partyIdInfo.partySubIdOrType | C11: Yes | J11: A sub-identifier or sub-type for the Party.
A12: payee.partyIdInfo.fspId | B12: payee.partyIdInfo.fspId | C12: Yes | F12: payeeFsp | G12: Yes | J12: The FSP identifier. | K12: Payee FSP in the proposed financial transaction.
A13: payee.partyIdInfo.extensionList | B13: payee.partyIdInfo.extensionList | C13: N/A | J13: Optional list of extensions to the payee information, specific to deployment.
A14: payee.partyIdInfo.extensionList.extension | B14: payee.partyIdInfo.extensionList.extension | C14: N/A | J14: An optional extension element defined by a key-value pair
A15: payee.partyIdInfo.extensionList.extension.key | B15: payee.partyIdInfo.extensionList.extension.key | C15: No | J15: The key for an optional extension element value
A16: payee.partyIdInfo.extensionList.extension.value | B16: payee.partyIdInfo.extensionList.extension.value | C16: No | J16: The value for an optional extension element key
A17: payee.merchantClassificationCode | B17: payee.merchantClassificationCode | C17: Yes | J17: A limited set of pre-defined numbers. This list would be a limited set of numbers identifying a set of popular merchant types like School Fees, Pubs and Restaurants, Groceries, and so on.
A18: payee.name | B18: payee.name | C18: Yes | J18: The name of the party, could be a real name or a nick name.
A19: payee.personalInfo | B19: payee.personalInfo | C19: N/A | J19: Personal information used to verify identity of Party such as first, middle, last name and date of birth.
A20: payee.personalInfo.complexName | B20: payee.personalInfo.complexName | C20: N/A | J20: First, middle and last name.
A21: payee.personalInfo.complexName.firstName | B21: payee.personalInfo.complexName.firstName | C21: Yes | J21: First name
A22: payee.personalInfo.complexName.middleName | B22: payee.personalInfo.complexName.middleName | C22: Yes | J22: Middle name
A23: payee.personalInfo.complexName.lastName | B23: payee.personalInfo.complexName.lastName | C23: Yes | J23: Last name
A24: payee.personalInfo.dateOfBirth | B24: payee.personalInfo.dateOfBirth | C24: Yes | J24: Date of birth
... A29: payer.partyIdInfo.partySubIdOrType | B29: payer.partyIdInfo.partySubIdOrType | C29: Yes | J29: A sub-identifier or sub-type for the Party.
A30: payer.partyIdInfo.fspId | B30: payer.partyIdInfo.fspId | C30: Yes | F30: payerFsp | G30: Yes | J30: The FSP identifier. | K30: Payer FSP in the proposed financial transaction.
A31: payer.partyIdInfo.extensionList | B31: payer.partyIdInfo.extensionList | C31: N/A | J31: Optional list of extensions to the payer information, specific to deployment.
A32: payer.partyIdInfo.extensionList.extension | B32: payer.partyIdInfo.extensionList.extension | C32: N/A | J32: An optional extension element defined by a key-value pair
A33: payer.partyIdInfo.extensionList.extension.key | B33: payer.partyIdInfo.extensionList.extension.key | C33: No | J33: The key for an optional extension element value
A34: payer.partyIdInfo.extensionList.extension.value | B34: payer.partyIdInfo.extensionList.extension.value | C34: No | J34: The value for an optional extension element key
A35: payer.merchantClassificationCode | B35: payer.merchantClassificationCode | C35: Yes | J35: A limited set of pre-defined numbers. This list would be a limited set of numbers identifying a set of popular merchant types like School Fees, Pubs and Restaurants, Groceries, and so on.
A36: payer.name | B36: payer.name | C36: Yes | J36: The name of the party, could be a real name or a nick name.
A37: payer.personalInfo | B37: payer.personalInfo | C37: N/A | J37: Personal information used to verify identity of Party such as first, middle, last name and date of birth.
A38: payer.personalInfo.complexName | B38: payer.personalInfo.complexName | C38: N/A | J38: First, middle and last name.
A39: payer.personalInfo.complexName.firstName | B39: payer.personalInfo.complexName.firstName | C39: Yes | J39: First name
A40: payer.personalInfo.complexName.middleName | B40: payer.personalInfo.complexName.middleName | C40: Yes | J40: Middle name
A41: payer.personalInfo.complexName.lastName | B41: payer.personalInfo.complexName.lastName | C41: Yes | J41: Last name
A42: payer.personalInfo.dateOfBirth | B42: payer.personalInfo.dateOfBirth | C42: Yes | J42: Date of birth
A43: amountType | B43: amountType | C43: No | J43: This element contains the amount type. Allowed values are: SEND (The amount the Payer would like to send, that is, the amount that should be withdrawn from the Payer account including any fees.) or RECEIVE (The amount the Payer would like the Payee to receive, that is, the amount that should be sent to the receiver exclusive fees.)
A44: amount | B44: amount | C44: Yes | F44: amount | G44: N/A | J44: Depending on amountType: If SEND: The amount the Payer would like to send, that is, the amount that should be withdrawn from the Payer account including any fees. The amount is updated by each participating entity in the transaction. If RECEIVE: The amount the Payee should receive, that is, the amount that should be sent to the receiver exclusive any fees. The amount is not updated by any of the participating entities.
A45: amount.currency | B45: amount.currency | C45: Yes | F45: amount.currency | G45: Yes | J45: The currency of the amount.
A46: amount.amount | B46: amount.amount | C46: Yes | F46: amount.amount | G46: Yes | J46: The value of the amount of money.
A47: fees | B47: fees | C47: N/A | J47: The fees in the transaction.
A48: fees.currency | B48: fees.currency | C48: Yes | J48: The currency of the fees amount.
A49: fees.amount | B49: fees.amount | C49: Yes | J49: The value of the fees amount
A50: transferAmount | D50: transferAmount | E50: N/A | J50: The amount of Money that the Payer FSP should transfer to the Payee FSP.
A51: transferAmount.currency | D51: transferAmount.currency | E51: Yes | J51: The currency of the transfer amount.
A52: transferAmount.amount | D52: transferAmount.amount | E52: Yes | J52: The value of the transfer amount
A53: payeeReceiveAmount | D53: payeeReceiveAmount | E53: N/A | J53: Amount that the Payee should receive in the end-to-end transaction. Optional as the Payee FSP might not want to disclose any optional Payee fees.
A54: payeeReceiveAmount.currency | D54: payeeReceiveAmount.currency | E54: Yes | J54: The currency of the payee receive amount.
A55: payeeReceiveAmount.amount | D55: payeeReceiveAmount.amount | E55: Yes | J55: The value of the payee receive amount
A56: payeeFspFee | D56: payeeFspFee | E56: N/A | J56: Payee FSP’s part of the transaction fee.
A57: payeeFspFee.currency | D57: payeeFspFee.currency | E57: Yes | J57: The currency of the fees amount.
A58: payeeFspFee.amount | D58: payeeFspFee.amount | E58: Yes | J58: The value of the fees amount
A59: payeeFspCommission | D59: payeeFspCommission | E59: N/A | J59: Transaction commission from the Payee FSP.
A60: payeeFspCommission.currency | D60: payeeFspCommission.currency | E60: Yes | J60: The currency of the payee FSP commission amount.
A61: payeeFspCommission.amount | D61: payeeFspCommission.amount | E61: Yes | J61: The value of the payee FSP commission amount
A62: transactionType | B62: transactionType | C62: N/A | J62: The type of transaction that the quote is requested for.
A63: transactionType.scenario | B63: transactionType.scenario | C63: Yes | J63: The nature of the transaction that the quote is requested for
A64: transactionType.subScenario | B64: transactionType.subScenario | C64: Yes | J64: Possible sub-scenario, defined locally within the scheme.
A65: transactionType.initiator | B65: transactionType.initiator | C65: No | J65: Who is initiating the transaction: payer or payee
A66: transactionType.initiatorType | B66: transactionType.initiatorType | C66: Yes | J66: The type of party initiating the transaction that the quote is requested for
A67: transactionType.refundInfo | B67: transactionType.refundInfo | C67: N/A | J67: Extra information specific to a refund scenario. Should only be populated if scenario is REFUND.
A68: transactionType.refundInfo.originalTransactionId | B68: transactionType.refundInfo.originalTransactionId | C68: No | J68: Reference to the original transaction ID that is requested to be refunded.
A69: transactionType.refundInfo.refundReason | B69: transactionType.refundInfo.refundReason | C69: No | J69: Free text indicating the reason for the refund.
A70: transactionType.balanceOfPayments | B70: transactionType.balanceOfPayments | C70: Yes | J70: Balance of Payments code.
A71: geoCode | B71: geoCode | C71: N/A | D71: geoCode | E71: N/A | J71: Longitude and Latitude of the initiating Party. Can be used to detect fraud.
A72: geoCode.latitude | B72: geoCode.latitude | C72: Yes | D72: geoCode.latitude | E72: Yes | J72: The Latitude of the service initiating Party.
A73: geoCode.longitude | B73: geoCode.longitude | C73: Yes | D73: geoCode.longitude | E73: Yes | J73: The Longitude of the service initiating Party.
A74: note | B74: note | C74: Yes | J74: A memo that will be attached to the transaction.
A75: expiration | B75: expiration | C75: Yes | D75: expiration | E75: Yes | F75: expiration | G75: Yes | J75: Expiration is optional. It can be set to get a quick failure in case the peer FSP takes too long to respond. Also, it may be beneficial for Consumer, Agent, and Merchant to know that their request has a time limit.
A76: fulfilment | H76: fulfilment | I76: No | J76: The fulfilment is a temporary secret that is generated for each financial transaction by the Payee FSP and used as the trigger to commit the transfers that make up an ILP payment, i.e. the fulfilment of the condition specified with the transaction. Mandatory if transfer has completed successfully.
A77: completedTimestamp | H77: completedTimestamp | I77: Yes | J77: Time and date when the transaction was completed
A78: transferState | H78: transferState | I78: Yes | J78: State of the transfer
A79: ilpPacket | D79: ilpPacket | E79: No | F79: ilpPacket | G79: No | J79: ILP Packet that must be attached to the transfer by the Payer.
A80: condition | D80: condition | E80: No | F80: condition | G80: No | J80: Condition that must be attached to the transfer by the Payer.
A81: extensionList | B81: extensionList | C81: N/A | D81: extensionList | E81: N/A | F81: extensionList | G81: N/A | H81: extensionList | I81: N/A | J81: Optional list of extensions to the quote or transfer, specific to deployment.
A82: extensionList.extension | B82: extensionList.extension | C82: N/A | D82: extensionList.extension | E82: N/A | F82: extensionList.extension | G82: N/A | H82: extensionList.extension | I82: N/A | J82: An optional extension element defined by a key-value pair
A83: extensionList.extension.key | B83: extensionList.extension.key | C83: No | D83: extensionList.extension.key | E83: No | F83: extensionList.extension.key | G83: No | H83: extensionList.extension.key | I83: No | J83: The key for an optional extension element value
A84: extensionList.extension.value | B84: extensionList.extension.value | C84: No | D84: extensionList.extension.value | E84: No | F84: extensionList.extension.value | G84: No | H84: extensionList.extension.value | I84: No | J84: The value for an optional extension element key

Sheet pain.001.001.11
A1: ISO20022 data element | B1: Xpath | C1: Value | D1: Type | E1: Description | F1: Notes
A2: CustomerCreditTransferInitiationV11.GroupHeader.MessageIdentification | B2: Document.CstmrCdtTrfInitn.GrpHdr.MsgId | C2: Generate fresh UUID | D2: Max35Text | E2: Point to point reference, as assigned by the instructing party, and sent to the next party in the chain to unambiguously identify the message.
A3: CustomerCreditTransferInitiationV11.GroupHeader.CreationDateTime | B3: Document.CstmrCdtTrfInitn.GrpHdr.CreDtTm | C3: Timestamp at the time the message is received by the TMS API | D3: ISODateTime | E3: Date and time at which the message was created.
A4: CustomerCreditTransferInitiationV11.GroupHeader.NumberOfTransactions | B4: Document.CstmrCdtTrfInitn.GrpHdr.NbOfTxs | C4: 1 | D4: Max15NumericText | E4: Number of individual transactions contained in the message.
A5: CustomerCreditTransferInitiationV11.GroupHeader.InitiatingParty.Name | B5: Document.CstmrCdtTrfInitn.GrpHdr.InitgPty.Nm | C5: ="IF " & Comparison!$B$65& " = 'PAYER' THEN " & A14 & " ELSE " & A32 -> IF transactionType.initiator = 'PAYER' THEN CustomerCreditTransferInitiationV11.PaymentInformation.Debtor.Name ELSE CustomerCreditTransferInitiationV11.PaymentInformation.CreditTransferTransactionInformation.Creditor.Name | D5: Max140Text | E5: Name by which a party is known and which is usually used to identify that party.
A6: CustomerCreditTransferInitiationV11.GroupHeader.InitiatingParty.Identification.PrivateIdentification.DateAndPlaceOfBirth.BirthDate | C6: ="IF " & Comparison!$B$65& " = 'PAYER' THEN " & A15 & " ELSE " & A33 -> IF transactionType.initiator = 'PAYER' THEN CustomerCreditTransferInitiationV11.PaymentInformation.Debtor.Identification.PrivateIdentification.DateAndPlaceOfBirth.BirthDate ELSE CustomerCreditTransferInitiationV11.PaymentInformation.CreditTransferTransactionInformation.Creditor.Identification.PrivateIdentification.DateAndPlaceOfBirth.BirthDate | D6: ISODate | E6: Unique and unambiguous identification of a party.
A7: CustomerCreditTransferInitiationV11.GroupHeader.InitiatingParty.Identification.PrivateIdentification.Other.Identification | C7: ="IF " & Comparison!$B$65& " = 'PAYER' THEN " & A16 & " ELSE " & A34 -> IF transactionType.initiator = 'PAYER' THEN CustomerCreditTransferInitiationV11.PaymentInformation.Debtor.Identification.PrivateIdentification.Other.Identification ELSE CustomerCreditTransferInitiationV11.PaymentInformation.CreditTransferTransactionInformation.Creditor.Identification.PrivateIdentification.Other.Identification | D7: Max35Text | E7: Unique and unambiguous identification of a person.
A8: CustomerCreditTransferInitiationV11.GroupHeader.InitiatingParty.Identification.PrivateIdentification.Other.SchemeName.Proprietary | C8: ="IF " & Comparison!$B$65& " = 'PAYER' THEN " & A17 & " ELSE " & A35 -> IF transactionType.initiator = 'PAYER' THEN CustomerCreditTransferInitiationV11.PaymentInformation.Debtor.Identification.PrivateIdentification.Other.SchemeName.Proprietary ELSE CustomerCreditTransferInitiationV11.PaymentInformation.CreditTransferTransactionInformation.Creditor.Identification.PrivateIdentification.Other.SchemeName.Proprietary | D8: Max35Text | E8: Name of the identification scheme, in a free text form.
A9: CustomerCreditTransferInitiationV11.GroupHeader.InitiatingParty.ContactDetails.MobileNumber | C9: ="IF " & Comparison!$B$65& " = 'PAYER' THEN " & A18 & " ELSE " & A36 -> IF transactionType.initiator = 'PAYER' THEN CustomerCreditTransferInitiationV11.PaymentInformation.Debtor.ContactDetails.MobileNumber ELSE CustomerCreditTransferInitiationV11.PaymentInformation.CreditTransferTransactionInformation.Creditor.ContactDetails.MobileNumber | D9: PhoneNumber | E9: Collection of information that identifies a mobile phone number, as defined by telecom services.
A10: CustomerCreditTransferInitiationV11.PaymentInformation.PaymentInformationIdentification | C10: =Comparison!B3 -> quoteId | D10: Max35Text | E10: Unique identification, as assigned by a sending party, to unambiguously identify the payment information group within the message.
A11: CustomerCreditTransferInitiationV11.PaymentInformation.PaymentMethod | C11: TRA | D11: PaymentMethod3Code | E11: Specifies the transfer method that will be used to transfer the cash. (TRA - TransferAdvice: Transfer of an amount of money in the books of the account servicer. An advice should be sent back to the account owner.)
A12: CustomerCreditTransferInitiationV11.PaymentInformation.RequestedAdviceType.DebitAdvice.Code | C12: ADWD | D12: PaymentMethod3Code | E12: Specifies the transfer method that will be used to transfer the cash. (TRA - TransferAdvice: Transfer of an amount of money in the books of the account servicer. An advice should be sent back to the account owner.)
A13: CustomerCreditTransferInitiationV11.PaymentInformation.RequestedExecutionDate.DateTime | C13: =A3 -> CustomerCreditTransferInitiationV11.GroupHeader.CreationDateTime | D13: ISODateTime | E13: Date at which the initiating party requests the clearing agent to process the payment. Usage: This is the date on which the debtor's account is to be debited. If payment by cheque, the date when the cheque must be generated by the bank. | F13: This is a mandatory field in the ISO message, though this does not make a lot of sense in an instant payments environment. For now, set this date the same as the message creation date/time
A14: CustomerCreditTransferInitiationV11.PaymentInformation.Debtor.Name | C14: =Comparison!B39 & " & " & Comparison!B40 & " & " & Comparison!B41 -> payer.personalInfo.complexName.firstName & payer.personalInfo.complexName.middleName & payer.personalInfo.complexName.lastName | D14: Max140Text | E14: Name by which a party is known and which is usually used to identify that party.
A15: CustomerCreditTransferInitiationV11.PaymentInformation.Debtor.Identification.PrivateIdentification.DateAndPlaceOfBirth.BirthDate | C15: =Comparison!B42 -> payer.personalInfo.dateOfBirth | D15: ISODate | E15: Unique and unambiguous identification of a party.
A16: CustomerCreditTransferInitiationV11.PaymentInformation.Debtor.Identification.PrivateIdentification.Other.Identification | C16: =Comparison!B28 -> payer.partyIdInfo.partyIdentifier | D16: Max35Text | E16: Unique and unambiguous identification of a person.
A17: CustomerCreditTransferInitiationV11.PaymentInformation.Debtor.Identification.PrivateIdentification.Other.SchemeName.Proprietary | C17: ="IF "&Comparison!B27& " = 'PERSONAL_ID' THEN "&Comparison!B29&" ELSE "&Comparison!B27 -> IF payer.partyIdInfo.partyIdType = 'PERSONAL_ID' THEN payer.partyIdInfo.partySubIdOrType ELSE payer.partyIdInfo.partyIdType | D17: Max35Text | E17: Name of the identification scheme, in a free text form.
A18: CustomerCreditTransferInitiationV11.PaymentInformation.Debtor.ContactDetails.MobileNumber | C18: ="IF "&Comparison!B27& " = 'MSISDN' THEN "&Comparison!B28&" ELSE NULL" -> IF payer.partyIdInfo.partyIdType = 'MSISDN' THEN payer.partyIdInfo.partyIdentifier ELSE NULL | D18: PhoneNumber | E18: Collection of information that identifies a mobile phone number, as defined by telecom services.
A19: CustomerCreditTransferInitiationV11.PaymentInformation.DebtorAccount.Identification.Other.Identification | C19: =Comparison!B28 -> payer.partyIdInfo.partyIdentifier | D19: Max34Text | E19: Identification assigned by an institution.
A20: CustomerCreditTransferInitiationV11.PaymentInformation.DebtorAccount.Identification.Other.Identification.SchemeName.Proprietary | C20: ="IF "&Comparison!B27& " = 'PERSONAL_ID' THEN "&Comparison!B29&" ELSE "&Comparison!B27 -> IF payer.partyIdInfo.partyIdType = 'PERSONAL_ID' THEN payer.partyIdInfo.partySubIdOrType ELSE payer.partyIdInfo.partyIdType | D20: Max35Text | E20: Name of the identification scheme, in a free text form.
A21: CustomerCreditTransferInitiationV11.PaymentInformation.DebtorAccount.Name | C21: =Comparison!B36 -> payer.name | D21: Max70Text | E21: Name of the account, as assigned by the account servicing institution, in agreement with the account owner in order to provide an additional means of identification of the account. Usage: The account name is different from the account owner name. The account name is used in certain user communities to provide a means of identifying the account, in addition to the account owner's identity and the account number.
A22: CustomerCreditTransferInitiationV11.PaymentInformation.DebtorAgent.FinancialInstitutionIdentification.ClearingSystemMemberIdentification.MemberIdentification | C22: =Comparison!B30 -> payer.partyIdInfo.fspId | D22: Max35Text | E22: Identification of a member of a clearing system.
A23: CustomerCreditTransferInitiationV11.PaymentInformation.CreditTransferTransactionInformation.PaymentIdentification.EndToEndIdentification | C23: =Comparison!B4 -> transactionId | D23: Max35Text | E23: Unique identification assigned by the initiating party to unambiguously identify the transaction. This identification is passed on, unchanged, throughout the entire end-to-end chain. Usage: The end-to-end identification can be used for reconciliation or to link tasks relating to the transaction. It can be included in several messages related to the transaction. | F23: This might be the CustomerCreditTransferInitiationV11.PaymentInformation.CreditTransferTransactionInformation.PaymentIdentification.UETR instead since it is a UUIDv4 Identifier. To be confirmed.
A24: CustomerCreditTransferInitiation.PaymentInformation.CreditTransferTransaction.PaymentTypeInformation.CategoryPurpose.Proprietary | C24: ="IF " & Comparison!B64 & " = NULL THEN " & Comparison!B63 & " ELSE " & Comparison!B63 & " & " & Comparison!B64 -> IF transactionType.subScenario = NULL THEN transactionType.scenario ELSE transactionType.scenario & transactionType.subScenario | D24: Max35Text | E24: Specifies the high level purpose of the instruction based on a set of pre-defined categories. Usage: This is used by the initiating party to provide information concerning the processing of the payment. It is likely to trigger special processing by any of the agents involved in the payment chain.
A25: CustomerCreditTransferInitiationV11.PaymentInformation.CreditTransferTransactionInformation.Amount.InstructedAmount.Amount | C25: ="IF " & Comparison!B43 & " = 'SEND' THEN " & Comparison!B46 & " ELSE " & Comparison!B46 & " + " & Comparison!B49 -> IF amountType = 'SEND' THEN amount.amount ELSE amount.amount + fees.amount | D25: ActiveOrHistoricCurrencyAndAmount | E25: Amount of money to be moved between the debtor and creditor, before deduction of charges, expressed in the currency as ordered by the initiating party. Usage: This amount has to be transported unchanged through the transaction chain.
A26: CustomerCreditTransferInitiationV11.PaymentInformation.CreditTransferTransactionInformation.Amount.InstructedAmount.Currency | C26: =Comparison!B45 -> amount.currency | D26: ActiveOrHistoricCurrencyAndAmount | E26: Amount of money to be moved between the debtor and creditor, before deduction of charges, expressed in the currency as ordered by the initiating party. Usage: This amount has to be transported unchanged through the transaction chain.
A27: CustomerCreditTransferInitiationV11.PaymentInformation.CreditTransferTransactionInformation.Amount.EquivalentAmount.Amount | C27: ="IF " & Comparison!B43 & " = 'SEND' THEN " & Comparison!B46 & " ELSE " & Comparison!B46 & " + " & Comparison!B49 -> IF amountType = 'SEND' THEN amount.amount ELSE amount.amount + fees.amount | D27: ActiveOrHistoricCurrencyAndAmount | E27: Amount of money to be moved between debtor and creditor, before deduction of charges, expressed in the currency of the debtor's account, and to be moved in a different currency. Usage: The first agent will convert the equivalent amount into the amount to be moved.
A28: CustomerCreditTransferInitiationV11.PaymentInformation.CreditTransferTransactionInformation.Amount.EquivalentAmount.Currency | C28: =Comparison!B45 -> amount.currency | D28: ActiveOrHistoricCurrencyAndAmount | E28: Amount of money to be moved between debtor and creditor, before deduction of charges, expressed in the currency of the debtor's account, and to be moved in a different currency. Usage: The first agent will convert the equivalent amount into the amount to be moved.
A29: CustomerCreditTransferInitiationV11.PaymentInformation.CreditTransferTransactionInformation.Amount.EquivalentAmount.CurrencyOfTransfer | C29: =Comparison!B45 -> amount.currency | D29: ActiveOrHistoricCurrencyCode | E29: Specifies the currency of the to be transferred amount, which is different from the currency of the debtor's account.
A30: CustomerCreditTransferInitiationV11.PaymentInformation.CreditTransferTransactionInformation.ChargeBearer | C30: DEBT | D30: ChargeBearerTypeCode | E30: Specifies which party(ies) will pay charges due for processing of the instruction.
A31: CustomerCreditTransferInitiationV11.PaymentInformation.CreditTransferTransactionInformation.CreditorAgent.FinancialInstitutionIdentification.ClearingSystemMemberIdentification.MemberIdentification | C31: =Comparison!B12 -> payee.partyIdInfo.fspId | D31: Max35Text | E31: Identification of a member of a clearing system.
A32: CustomerCreditTransferInitiationV11.PaymentInformation.CreditTransferTransactionInformation.Creditor.Name | C32: =Comparison!B21 & " & " & Comparison!B22 & " & " & Comparison!B23 -> payee.personalInfo.complexName.firstName & payee.personalInfo.complexName.middleName & payee.personalInfo.complexName.lastName | D32: Max140Text | E32: Name by which a party is known and which is usually used to identify that party.
A33: CustomerCreditTransferInitiationV11.PaymentInformation.CreditTransferTransactionInformation.Creditor.Identification.PrivateIdentification.DateAndPlaceOfBirth.BirthDate | C33: =Comparison!B24 -> payee.personalInfo.dateOfBirth | D33: ISODate | E33: Unique and unambiguous identification of a party.
A34: CustomerCreditTransferInitiationV11.PaymentInformation.CreditTransferTransactionInformation.Creditor.Identification.PrivateIdentification.Other.Identification | C34: =Comparison!B10 -> payee.partyIdInfo.partyIdentifier | D34: Max35Text | E34: Unique and unambiguous identification of a person.
A35: CustomerCreditTransferInitiationV11.PaymentInformation.CreditTransferTransactionInformation.Creditor.Identification.PrivateIdentification.Other.SchemeName.Proprietary | C35: ="IF "&Comparison!B9& " = 'PERSONAL_ID' THEN "&Comparison!B11&" ELSE "&Comparison!B9 -> IF payee.partyIdInfo.partyIdType = 'PERSONAL_ID' THEN payee.partyIdInfo.partySubIdOrType ELSE payee.partyIdInfo.partyIdType | D35: Max35Text | E35: Name of the identification scheme, in a free text form.
A36: CustomerCreditTransferInitiationV11.PaymentInformation.CreditTransferTransactionInformation.Creditor.ContactDetails.MobileNumber | C36: ="IF "&Comparison!B9& " = 'MSISDN' THEN "&Comparison!B10&" ELSE NULL" -> IF payee.partyIdInfo.partyIdType = 'MSISDN' THEN payee.partyIdInfo.partyIdentifier ELSE NULL | D36: PhoneNumber | E36: Collection of information that identifies a mobile phone number, as defined by telecom services.
A37: CustomerCreditTransferInitiationV11.PaymentInformation.CreditTransferTransactionInformation.CreditorAccount.Identification.Other.Identification | C37: =Comparison!B28 -> payer.partyIdInfo.partyIdentifier | D37: Max34Text | E37: Identification assigned by an institution.
A38: CustomerCreditTransferInitiationV11.PaymentInformation.CreditTransferTransactionInformation.CreditorAccount.Identification.Other.Identification.SchemeName.Proprietary | C38: ="IF "&Comparison!B9& " = 'PERSONAL_ID' THEN "&Comparison!B11&" ELSE "&Comparison!B9 -> IF payee.partyIdInfo.partyIdType = 'PERSONAL_ID' THEN payee.partyIdInfo.partySubIdOrType ELSE payee.partyIdInfo.partyIdType | D38: Max35Text | E38: Name of the identification scheme, in a free text form.
A39: CustomerCreditTransferInitiationV11.PaymentInformation.CreditTransferTransactionInformation.CreditorAccount.Name | C39: =Comparison!B18 -> payee.name | D39: Max70Text | E39: Name of the account, as assigned by the account servicing institution, in agreement with the account owner in order to provide an additional means of identification of the account. Usage: The account name is different from the account owner name. The account name is used in certain user communities to provide a means of identifying the account, in addition to the account owner's identity and the account number.
A40: CustomerCreditTransferInitiationV11.PaymentInformation.CreditTransferTransactionInformation.Purpose.Code | C40: MP2P | D40: ExternalPurpose1Code | E40: Underlying reason for the payment transaction, as published in an external purpose code list. | F40: This code denotes a Mobile Person-to-Person payment, which is the pre-dominant use of Mojaloop. Merchant payments will be introduced at some point and some logic will be required to identify whether this code is MP2P or MP2B.
A41: CustomerCreditTransferInitiation.PaymentInformation.CreditTransferTransactionInformation.RegulatoryReporting.DebitCreditReportingIndicator | C41: BOTH | D41: RegulatoryReportingType1Code | E41: Identifies whether the regulatory reporting information applies to the debit side, to the credit side or to both debit and credit sides of the transaction.
A42: CustomerCreditTransferInitiation.PaymentInformation.CreditTransferTransactionInformation.RegulatoryReporting.Details.Type | C42: BALANCE OF PAYMENTS | D42: Max35Text | E42: Specifies the type of the information supplied in the regulatory reporting details.
A43: CustomerCreditTransferInitiation.PaymentInformation.CreditTransferTransactionInformation.RegulatoryReporting.Details.Code | C43: =Comparison!B70 -> transactionType.balanceOfPayments | D43: Max10Text | E43: Specifies the nature, purpose, and reason for the transaction to be reported for regulatory and statutory requirements in a coded form.
A44: CustomerCreditTransferInitiation.PaymentInformation.CreditTransferTransaction.RemittanceInformation.Unstructured | C44: =Comparison!B74 -> note | D44: Max140Text | E44: Information supplied to enable the matching/reconciliation of an entry with the items that the payment is intended to settle, such as commercial invoices in an accounts' receivable system, in an unstructured form.
A45: CustomerCreditTransferInitiationV11.PaymentInformation.CreditTransferTransactionInformation.SupplementaryData.Envelope.Document.Debtor.MerchantClassificationCode | C45: =Comparison!B35 -> payer.merchantClassificationCode
A46: CustomerCreditTransferInitiationV11.PaymentInformation.CreditTransferTransactionInformation.SupplementaryData.Envelope.Document.Creditor.MerchantClassificationCode | C46: =Comparison!B17 -> payee.merchantClassificationCode
A47: CustomerCreditTransferInitiationV11.PaymentInformation.CreditTransferTransactionInformation.SupplementaryData.Envelope.Document.PayerFspFees.Amount | C47: =Comparison!B49 -> fees.amount
A48: CustomerCreditTransferInitiationV11.PaymentInformation.CreditTransferTransactionInformation.SupplementaryData.Envelope.Document.PayerFspFees.Currency | C48: =Comparison!B48 -> fees.currency
A49: CustomerCreditTransferInitiationV11.PaymentInformation.CreditTransferTransactionInformation.SupplementaryData.Envelope.Document.Expiration | C49: =Comparison!B75 -> expiration
A50: CustomerCreditTransferInitiationV11.SupplementaryData.Envelope.Document.InitiatingParty.InitiatorType | C50: =Comparison!B66 -> transactionType.initiatorType
A51: CustomerCreditTransferInitiationV11.SupplementaryData.Envelope.Document.InitiatingParty.GeoLocation.latitude | C51: =Comparison!B72 -> geoCode.latitude
A52: CustomerCreditTransferInitiationV11.SupplementaryData.Envelope.Document.InitiatingParty.GeoLocation.longitude | C52: =Comparison!B73 -> geoCode.longitude

Sheet pain.001.013.09
A1: ISO20022 data element | B1: Xpath | C1: Value | D1: Type | E1: Description | F1: Notes
A2: CreditorPaymentActivationRequestV09.GroupHeader.MessageIdentification | B2: Document.CstmrCdtTrfInitn.GrpHdr.MsgId | C2: Generate fresh UUID | D2: Max35Text | E2: Point to point reference, as assigned by the instructing party, and sent to the next party in the chain to unambiguously identify the message.
A3: CreditorPaymentActivationRequestV09.GroupHeader.CreationDateTime | B3: Document.CstmrCdtTrfInitn.GrpHdr.CreDtTm | C3: Timestamp at the time the message is received by the TMS API | D3: ISODateTime | E3: Date and time at which the message was created.
A4: CreditorPaymentActivationRequestV09.GroupHeader.NumberOfTransactions | B4: Document.CstmrCdtTrfInitn.GrpHdr.NbOfTxs | C4: 1 | D4: Max15NumericText | E4: Number of individual transactions contained in the message.
A5: CreditorPaymentActivationRequestV09.GroupHeader.InitiatingParty.Name | B5: Document.CstmrCdtTrfInitn.GrpHdr.InitgPty.Nm | C5: ='pain.001.001.11'!A5 & " {" & $C$10 & "}" -> CustomerCreditTransferInitiationV11.GroupHeader.InitiatingParty.Name {quoteId (from URI)} | D5: Max140Text | E5: Name by which a party is known and which is usually used to identify that party. | F5: Added through enrichment
A6: CreditorPaymentActivationRequestV09.GroupHeader.InitiatingParty.Identification.PrivateIdentification.DateAndPlaceOfBirth.BirthDate | C6: ='pain.001.001.11'!A6 & " {" & $C$10 & "}" -> CustomerCreditTransferInitiationV11.GroupHeader.InitiatingParty.Identification.PrivateIdentification.DateAndPlaceOfBirth.BirthDate {quoteId (from URI)} | D6: ISODate | E6: Unique and unambiguous identification of a party. | F6: Added through enrichment
A7: CreditorPaymentActivationRequestV09.GroupHeader.InitiatingParty.Identification.PrivateIdentification.Other.Identification | C7: ='pain.001.001.11'!A7 & " {" & $C$10 & "}" -> CustomerCreditTransferInitiationV11.GroupHeader.InitiatingParty.Identification.PrivateIdentification.Other.Identification {quoteId (from URI)} | D7: Max35Text | E7: Unique and unambiguous identification of a person. | F7: Added through enrichment
A8: CreditorPaymentActivationRequestV09.GroupHeader.InitiatingParty.Identification.PrivateIdentification.Other.SchemeName.Proprietary | C8: ='pain.001.001.11'!A8 & " {" & $C$10 & "}" -> CustomerCreditTransferInitiationV11.GroupHeader.InitiatingParty.Identification.PrivateIdentification.Other.SchemeName.Proprietary {quoteId (from URI)} | D8: Max35Text | E8: Name of the identification scheme, in a free text form. | F8: Added through enrichment
A9: CreditorPaymentActivationRequestV09.GroupHeader.InitiatingParty.ContactDetails.MobileNumber | C9: ='pain.001.001.11'!A9 & " {" & $C$10 & "}" -> CustomerCreditTransferInitiationV11.GroupHeader.InitiatingParty.ContactDetails.MobileNumber {quoteId (from URI)} | D9: PhoneNumber | E9: Collection of information that identifies a mobile phone number, as defined by telecom services. | F9: Added through enrichment
A10: CreditorPaymentActivationRequestV09.PaymentInformation.PaymentInformationIdentification | C10: =Comparison!D3 -> quoteId (from URI) | D10: Max35Text | E10: Unique identification, as assigned by a sending party, to unambiguously identify the payment information group within the message. | F10: Retrieved from incoming message URI
A11: CreditorPaymentActivationRequestV09.PaymentInformation.PaymentMethod | C11: ='pain.001.001.11'!A11 & " {" & $C$10 & "}" -> CustomerCreditTransferInitiationV11.PaymentInformation.PaymentMethod {quoteId (from URI)} | D11: PaymentMethod3Code | E11: Specifies the transfer method that will be used to transfer the cash. (TRA - TransferAdvice: Transfer of an amount of money in the books of the account servicer. An advice should be sent back to the account owner.) | F11: Added through enrichment
A12: CreditorPaymentActivationRequestV09.PaymentInformation.RequestedAdviceType.DebitAdvice.Code | C12: ='pain.001.001.11'!A12 & " {" & $C$10 & "}" -> CustomerCreditTransferInitiationV11.PaymentInformation.RequestedAdviceType.DebitAdvice.Code {quoteId (from URI)} | D12: PaymentMethod3Code | E12: Specifies the transfer method that will be used to transfer the cash. (TRA - TransferAdvice: Transfer of an amount of money in the books of the account servicer. An advice should be sent back to the account owner.) | F12: Added through enrichment
A13: CreditorPaymentActivationRequestV09.PaymentInformation.RequestedExecutionDate.DateTime | C13: =A3 -> CreditorPaymentActivationRequestV09.GroupHeader.CreationDateTime | D13: ISODateTime | E13: Date at which the initiating party requests the clearing agent to process the payment. Usage: This is the date on which the debtor's account is to be debited. If payment by cheque, the date when the cheque must be generated by the bank. | F13: This is a mandatory field in the ISO message, though this does not make a lot of sense in an instant payments environment. For now, set this date the same as the message creation date/time
A14: CreditorPaymentActivationRequestV09.PaymentInformation.ExpiryDate.DateTime | C14: =Comparison!D75 -> expiration | D14: ISODateTime | E14: Date by which the debtor must have accepted or rejected the request. Usage: Beyond this date, the request becomes void and cannot be processed anymore.
A15: CreditorPaymentActivationRequestV09.PaymentInformation.Debtor.Name | C15: ='pain.001.001.11'!A14 & " {" & $C$10 & "}" -> CustomerCreditTransferInitiationV11.PaymentInformation.Debtor.Name {quoteId (from URI)} | D15: Max140Text | E15: Name by which a party is known and which is usually used to identify that party. | F15: Added through enrichment
A16: CreditorPaymentActivationRequestV09.PaymentInformation.Debtor.Identification.PrivateIdentification.DateAndPlaceOfBirth.BirthDate | C16: ='pain.001.001.11'!A15 & " {" & $C$10 & "}" -> CustomerCreditTransferInitiationV11.PaymentInformation.Debtor.Identification.PrivateIdentification.DateAndPlaceOfBirth.BirthDate {quoteId (from URI)} | D16: ISODate | E16: Unique and unambiguous identification of a party. | F16: Added through enrichment
A17: CreditorPaymentActivationRequestV09.PaymentInformation.Debtor.Identification.PrivateIdentification.Other.Identification | C17: ='pain.001.001.11'!A16 & " {" & $C$10 & "}" -> CustomerCreditTransferInitiationV11.PaymentInformation.Debtor.Identification.PrivateIdentification.Other.Identification {quoteId (from URI)} | D17: Max35Text | E17: Unique and unambiguous identification of a person. | F17: Added through enrichment
A18: CreditorPaymentActivationRequestV09.PaymentInformation.Debtor.Identification.PrivateIdentification.Other.SchemeName.Proprietary | C18: ='pain.001.001.11'!A17 & " {" & $C$10 & "}" -> CustomerCreditTransferInitiationV11.PaymentInformation.Debtor.Identification.PrivateIdentification.Other.SchemeName.Proprietary {quoteId (from URI)} | D18: Max35Text | E18: Name of the identification scheme, in a free text form. | F18: Added through enrichment
A19: CreditorPaymentActivationRequestV09.PaymentInformation.Debtor.ContactDetails.MobileNumber | C19: ='pain.001.001.11'!A18 & " {" & $C$10 & "}" -> CustomerCreditTransferInitiationV11.PaymentInformation.Debtor.ContactDetails.MobileNumber {quoteId (from URI)} | D19: PhoneNumber | E19: Collection of information that identifies a mobile phone number, as defined by telecom services. | F19: Added through enrichment
A20: CreditorPaymentActivationRequestV09.PaymentInformation.DebtorAccount.Identification.Other.Identification | C20: ='pain.001.001.11'!A19 & " {" & $C$10 & "}" -> CustomerCreditTransferInitiationV11.PaymentInformation.DebtorAccount.Identification.Other.Identification {quoteId (from URI)} | D20: Max34Text | E20: Identification assigned by an institution. | F20: Added through enrichment
A21: CreditorPaymentActivationRequestV09.PaymentInformation.DebtorAccount.Identification.Other.Identification.SchemeName.Proprietary | C21: ='pain.001.001.11'!A20 & " {" & $C$10 & "}" -> CustomerCreditTransferInitiationV11.PaymentInformation.DebtorAccount.Identification.Other.Identification.SchemeName.Proprietary {quoteId (from URI)} | D21: Max35Text | E21: Name of the identification scheme, in a free text form. | F21: Added through enrichment
A22: CreditorPaymentActivationRequestV09.PaymentInformation.DebtorAccount.Name | C22: ='pain.001.001.11'!A21 & " {" & $C$10 & "}" -> CustomerCreditTransferInitiationV11.PaymentInformation.DebtorAccount.Name {quoteId (from URI)} | D22: Max70Text | E22: Name of the account, as assigned by the account servicing institution, in agreement with the account owner in order to provide an additional means of identification of the account. Usage: The account name is different from the account owner name. The account name is used in certain user communities to provide a means of identifying the account, in addition to the account owner's identity and the account number. | F22: Added through enrichment
A23: CreditorPaymentActivationRequestV09.PaymentInformation.DebtorAgent.FinancialInstitutionIdentification.ClearingSystemMemberIdentification.MemberIdentification | C23: ='pain.001.001.11'!A22 & " {" & $C$10 & "}" -> CustomerCreditTransferInitiationV11.PaymentInformation.DebtorAgent.FinancialInstitutionIdentification.ClearingSystemMemberIdentification.MemberIdentification {quoteId (from URI)} | D23: Max35Text | E23: Identification of a member of a clearing system. | F23: Added through enrichment
A24: CreditorPaymentActivationRequestV09.PaymentInformation.CreditTransferTransactionInformation.PaymentIdentification.EndToEndIdentification | C24: ='pain.001.001.11'!A23 & " {" & $C$10 & "}" -> CustomerCreditTransferInitiationV11.PaymentInformation.CreditTransferTransactionInformation.PaymentIdentification.EndToEndIdentification {quoteId (from URI)} | D24: Max35Text | E24: Unique identification assigned by the initiating party to unambiguously identify the transaction. This identification is passed on, unchanged, throughout the entire end-to-end chain. Usage: The end-to-end identification can be used for reconciliation or to link tasks relating to the transaction. It can be included in several messages related to the transaction. | F24: Added through enrichment
A25: CustomerCreditTransferInitiation.PaymentInformation.CreditTransferTransaction.PaymentTypeInformation.CategoryPurpose.Proprietary | C25: ='pain.001.001.11'!A24 & " {" & $C$10 & "}" -> CustomerCreditTransferInitiation.PaymentInformation.CreditTransferTransaction.PaymentTypeInformation.CategoryPurpose.Proprietary {quoteId (from URI)} | D25: Max35Text | E25: Specifies the high level purpose of the instruction based on a set of pre-defined categories. Usage: This is used by the initiating party to provide information concerning the processing of the payment. It is likely to trigger special processing by any of the agents involved in the payment chain. | F25: Added through enrichment
A26: CreditorPaymentActivationRequestV09.PaymentInformation.CreditTransferTransactionInformation.Amount.InstructedAmount.Amount | C26: =Comparison!D52 -> transferAmount.amount | D26: ActiveOrHistoricCurrencyAndAmount | E26: Amount of money to be moved between the debtor and creditor, before deduction of charges, expressed in the currency as ordered by the initiating party. Usage: This amount has to be transported unchanged through the transaction chain.
A27: CreditorPaymentActivationRequestV09.PaymentInformation.CreditTransferTransactionInformation.Amount.InstructedAmount.Currency | C27: =Comparison!D51 -> transferAmount.currency | D27: ActiveOrHistoricCurrencyAndAmount | E27: Amount of money to be moved between the debtor and creditor, before deduction of charges, expressed in the currency as ordered by the initiating party. Usage: This amount has to be transported unchanged through the transaction chain.
A28: CreditorPaymentActivationRequestV09.PaymentInformation.CreditTransferTransactionInformation.Amount.EquivalentAmount.Amount | C28: =Comparison!D52 -> transferAmount.amount | D28: ActiveOrHistoricCurrencyAndAmount | E28: Amount of money to be moved between debtor and creditor, before deduction of charges, expressed in the currency of the debtor's account, and to be moved in a different currency. Usage: The first agent will convert the equivalent amount into the amount to be moved.
A29: CreditorPaymentActivationRequestV09.PaymentInformation.CreditTransferTransactionInformation.Amount.EquivalentAmount.Currency | C29: =Comparison!D51 -> transferAmount.currency | D29: ActiveOrHistoricCurrencyAndAmount | E29: Amount of money to be moved between debtor and creditor, before deduction of charges, expressed in the currency of the debtor's account, and to be moved in a different currency. Usage: The first agent will convert the equivalent amount into the amount to be moved.
A30: CreditorPaymentActivationRequestV09.PaymentInformation.CreditTransferTransactionInformation.Amount.EquivalentAmount.CurrencyOfTransfer | C30: =Comparison!B45 -> amount.currency | D30: ActiveOrHistoricCurrencyCode | E30: Specifies the currency of the to be transferred amount, which is different from the currency of the debtor's account.
A31: CreditorPaymentActivationRequestV09.PaymentInformation.CreditTransferTransactionInformation.ChargeBearer | C31: DEBT | D31: ChargeBearerTypeCode | E31: Specifies which party(ies) will pay charges due for processing of the instruction.
A32: CreditorPaymentActivationRequestV09.PaymentInformation.CreditTransferTransactionInformation.CreditorAgent.FinancialInstitutionIdentification.ClearingSystemMemberIdentification.MemberIdentification | C32: ='pain.001.001.11'!A31 & " {" & $C$10 & "}" -> CustomerCreditTransferInitiationV11.PaymentInformation.CreditTransferTransactionInformation.CreditorAgent.FinancialInstitutionIdentification.ClearingSystemMemberIdentification.MemberIdentification {quoteId (from URI)} | D32: Max35Text | E32: Identification of a member of a clearing system. | F32: Added through enrichment
A33: CreditorPaymentActivationRequestV09.PaymentInformation.CreditTransferTransactionInformation.Creditor.Name | C33: ='pain.001.001.11'!A32 & " {" & $C$10 & "}" -> CustomerCreditTransferInitiationV11.PaymentInformation.CreditTransferTransactionInformation.Creditor.Name {quoteId (from URI)} | D33: Max140Text | E33: Name by which a party is known and which is usually used to identify that party. | F33: Added through enrichment
A34: CreditorPaymentActivationRequestV09.PaymentInformation.CreditTransferTransactionInformation.Creditor.Identification.PrivateIdentification.DateAndPlaceOfBirth.BirthDate | C34: ='pain.001.001.11'!A33 & " {" & $C$10 & "}" -> CustomerCreditTransferInitiationV11.PaymentInformation.CreditTransferTransactionInformation.Creditor.Identification.PrivateIdentification.DateAndPlaceOfBirth.BirthDate {quoteId (from URI)} | D34: ISODate | E34: Unique and unambiguous identification of a party. | F34: Added through enrichment
A35: CreditorPaymentActivationRequestV09.PaymentInformation.CreditTransferTransactionInformation.Creditor.Identification.PrivateIdentification.Other.Identification | C35: ='pain.001.001.11'!A34 & " {" & $C$10 & "}" -> CustomerCreditTransferInitiationV11.PaymentInformation.CreditTransferTransactionInformation.Creditor.Identification.PrivateIdentification.Other.Identification {quoteId (from URI)} | D35: Max35Text | E35: Unique and unambiguous identification of a person. | F35: Added through enrichment
A36: CreditorPaymentActivationRequestV09.PaymentInformation.CreditTransferTransactionInformation.Creditor.Identification.PrivateIdentification.Other.SchemeName.Proprietary | C36: ='pain.001.001.11'!A35 & " {" & $C$10 & "}" -> CustomerCreditTransferInitiationV11.PaymentInformation.CreditTransferTransactionInformation.Creditor.Identification.PrivateIdentification.Other.SchemeName.Proprietary {quoteId (from URI)} | D36: Max35Text | E36: Name of the identification scheme, in a free text form. | F36: Added through enrichment
A37: CreditorPaymentActivationRequestV09.PaymentInformation.CreditTransferTransactionInformation.Creditor.ContactDetails.MobileNumber | C37: ='pain.001.001.11'!A36 & " {" & $C$10 & "}" -> CustomerCreditTransferInitiationV11.PaymentInformation.CreditTransferTransactionInformation.Creditor.ContactDetails.MobileNumber {quoteId (from URI)} | D37: PhoneNumber | E37: Collection of information that identifies a mobile phone number, as defined by telecom services. | F37: Added through enrichment
A38: CreditorPaymentActivationRequestV09.PaymentInformation.CreditTransferTransactionInformation.CreditorAccount.Identification.Other.Identification | C38: ='pain.001.001.11'!A37 & " {" & $C$10 & "}" -> CustomerCreditTransferInitiationV11.PaymentInformation.CreditTransferTransactionInformation.CreditorAccount.Identification.Other.Identification {quoteId (from URI)} | D38: Max34Text | E38: Identification assigned by an institution. | F38: Added through enrichment
A39: CreditorPaymentActivationRequestV09.PaymentInformation.CreditTransferTransactionInformation.CreditorAccount.Identification.Other.Identification.SchemeName.Proprietary | C39: ='pain.001.001.11'!A38 & " {" & $C$10 & "}" -> CustomerCreditTransferInitiationV11.PaymentInformation.CreditTransferTransactionInformation.CreditorAccount.Identification.Other.Identification.SchemeName.Proprietary {quoteId (from URI)} | D39: Max35Text | E39: Name of the identification scheme, in a free text form. | F39: Added through enrichment
A40: CreditorPaymentActivationRequestV09.PaymentInformation.CreditTransferTransactionInformation.CreditorAccount.Name | C40: ='pain.001.001.11'!A39 & " {" & $C$10 & "}" -> CustomerCreditTransferInitiationV11.PaymentInformation.CreditTransferTransactionInformation.CreditorAccount.Name {quoteId (from URI)} | D40: Max70Text | E40: Name of the account, as assigned by the account servicing institution, in agreement with the account owner in order to provide an additional means of identification of the account. Usage: The account name is different from the account owner name. The account name is used in certain user communities to provide a means of identifying the account, in addition to the account owner's identity and the account number. | F40: Added through enrichment
A41: CreditorPaymentActivationRequestV09.PaymentInformation.CreditTransferTransactionInformation.Purpose.Code | C41: ='pain.001.001.11'!A40 & " {" & $C$10 & "}" -> CustomerCreditTransferInitiationV11.PaymentInformation.CreditTransferTransactionInformation.Purpose.Code {quoteId (from URI)} | D41: ExternalPurpose1Code | E41: Underlying reason for the payment transaction, as published in an external purpose code list. | F41: This code denotes a Mobile Person-to-Person payment, which is the pre-dominant use of Mojaloop. Merchant payments will be introduced at some point and some logic will be required to identify whether this code is MP2P or MP2B.
A42: CustomerCreditTransferInitiation.PaymentInformation.CreditTransferTransactionInformation.RegulatoryReporting.DebitCreditReportingIndicator | C42: ='pain.001.001.11'!A41 & " {" & $C$10 & "}" -> CustomerCreditTransferInitiation.PaymentInformation.CreditTransferTransactionInformation.RegulatoryReporting.DebitCreditReportingIndicator {quoteId (from URI)} | D42: RegulatoryReportingType1Code | E42: Identifies whether the regulatory reporting information applies to the debit side, to the credit side or to both debit and credit sides of the transaction. | F42: Added through enrichment
A43: CustomerCreditTransferInitiation.PaymentInformation.CreditTransferTransactionInformation.RegulatoryReporting.Details.Type | C43: ='pain.001.001.11'!A42 & " {" & $C$10 & "}" -> CustomerCreditTransferInitiation.PaymentInformation.CreditTransferTransactionInformation.RegulatoryReporting.Details.Type {quoteId (from URI)} | D43: Max35Text | E43: Specifies the type of the information supplied in the regulatory reporting details. | F43: Added through enrichment
A44: CustomerCreditTransferInitiation.PaymentInformation.CreditTransferTransactionInformation.RegulatoryReporting.Details.Code | C44: ='pain.001.001.11'!A43 & " {" & $C$10 & "}" -> CustomerCreditTransferInitiation.PaymentInformation.CreditTransferTransactionInformation.RegulatoryReporting.Details.Code {quoteId (from URI)} | D44: Max10Text | E44: Specifies the nature, purpose, and reason for the transaction to be reported for regulatory and statutory requirements in a coded form. | F44: Added through enrichment
A45: CreditorPaymentActivationRequestV09.PaymentInformation.CreditTransferTransactionInformation.SupplementaryData.Envelope.Document.PayeeReceiveAmount.Amount | C45: =Comparison!D55 -> payeeReceiveAmount.amount
A46: CreditorPaymentActivationRequestV09.PaymentInformation.CreditTransferTransactionInformation.SupplementaryData.Envelope.Document.PayeeReceiveAmount.Currency | C46: =Comparison!D54 -> payeeReceiveAmount.currency
A47: CreditorPaymentActivationRequestV09.PaymentInformation.CreditTransferTransactionInformation.SupplementaryData.Envelope.Document.PayeeFspFee.Amount | C47: =Comparison!D58 -> payeeFspFee.amount
A48: CreditorPaymentActivationRequestV09.PaymentInformation.CreditTransferTransactionInformation.SupplementaryData.Envelope.Document.PayeeFspFee.Currency | C48: =Comparison!D57 -> payeeFspFee.currency
A49: CreditorPaymentActivationRequestV09.PaymentInformation.CreditTransferTransactionInformation.SupplementaryData.Envelope.Document.PayeeFspCommission.Amount | C49: =Comparison!D61 -> payeeFspCommission.amount
A50: CreditorPaymentActivationRequestV09.PaymentInformation.CreditTransferTransactionInformation.SupplementaryData.Envelope.Document.PayeeFspCommission.Currency | C50: =Comparison!D60 -> payeeFspCommission.currency
A51: CreditorPaymentActivationRequestV09.SupplementaryData.Envelope.Document.InitiatingParty.GeoLocation.latitude | C51: =Comparison!B72 -> geoCode.latitude
A52: CreditorPaymentActivationRequestV09.SupplementaryData.Envelope.Document.InitiatingParty.GeoLocation.longitude | C52: =Comparison!B73 -> geoCode.longitude

Sheet pacs.008.001.10
A1: ISO20022 data element | B1: Xpath | C1: Value | D1: Type | E1: Description | F1: Notes
A2: FIToFICustomerCreditTransferV10.GroupHeader.MessageIdentification | B2: Document.CstmrCdtTrfInitn.GrpHdr.MsgId | C2: Generate fresh UUID | D2: Max35Text | E2: Point to point reference, as assigned by the instructing party, and sent to the next party in the chain to unambiguously identify the message.
A3: FIToFICustomerCreditTransferV10.GroupHeader.CreationDateTime | B3: Document.CstmrCdtTrfInitn.GrpHdr.CreDtTm | C3: Timestamp at the time the message is received by the TMS API | D3: ISODateTime | E3: Date and time at which the message was created.
A4: FIToFICustomerCreditTransferV10.GroupHeader.NumberOfTransactions | B4: Document.CstmrCdtTrfInitn.GrpHdr.NbOfTxs | C4: 1 | D4: Max15NumericText | E4: Number of individual transactions contained in the message.
A5: FIToFICustomerCreditTransferV10.GroupHeader.SettlementInformation.SettlementMethod | C5: CLRG | D5: SettlementMethod1Code | E5: Specifies the method used to settle the credit transfer instruction.
A6: FIToFICustomerCreditTransferV10.CreditTransferTransactionInformation.PaymentIdentification.InstructionIdentification | C6: ='pain.001.013.09'!A10 & " {" & Comparison!$F$5 & "}" -> CreditorPaymentActivationRequestV09.PaymentInformation.PaymentInformationIdentification {transferId} | D6: Max35Text | E6: Unique identification, as assigned by an instructing party for an instructed party, to unambiguously identify the instruction. Usage: The instruction identification is a point to point reference that can be used between the instructing party and the instructed party to refer to the individual instruction. It can be included in several messages related to the instruction. | F6: Enriched from Quote via TransferID
A7: FIToFICustomerCreditTransferV10.CreditTransferTransactionInformation.PaymentIdentification.EndToEndIdentification | C7: =Comparison!F5 -> transferId | D7: Max35Text | E7: Unique identification assigned by the initiating party to unambiguously identify the transaction. This identification is passed on, unchanged, throughout the entire end-to-end chain. Usage: The end-to-end identification can be used for reconciliation or to link tasks relating to the transaction. It can be included in several messages related to the transaction. | F7: This might be the CustomerCreditTransferInitiationV11.PaymentInformation.CreditTransferTransactionInformation.PaymentIdentification.UETR instead since it is a UUIDv4 Identifier. To be confirmed.
A8: FIToFICustomerCreditTransferV10.CreditTransferTransactionInformation.InterbankSettlementAmount.Amount | C8: =Comparison!F46 -> amount.amount | D8: ActiveCurrencyAndAmount | E8: Amount of money moved between the instructing agent and the instructed agent.
A9: FIToFICustomerCreditTransferV10.CreditTransferTransactionInformation.InterbankSettlementAmount.Currency | C9: =Comparison!F45 -> amount.currency | D9: ActiveCurrencyAndAmount | E9: Amount of money moved between the instructing agent and the instructed agent.
A10: FIToFICustomerCreditTransferV10.CreditTransferTransactionInformation.InstructedAmount.Amount | C10: ='pain.001.013.09'!A26 & " {" & Comparison!$F$5 & "}" -> CreditorPaymentActivationRequestV09.PaymentInformation.CreditTransferTransactionInformation.Amount.InstructedAmount.Amount {transferId} | D10: ActiveCurrencyAndAmount | E10: Amount of money moved between the instructing agent and the instructed agent. | F10: Enriched from Quote via TransferID
A11: FIToFICustomerCreditTransferV10.CreditTransferTransactionInformation.InstructedAmount.Currency | C11: ='pain.001.013.09'!A27 & " {" & Comparison!$F$5 & "}" -> CreditorPaymentActivationRequestV09.PaymentInformation.CreditTransferTransactionInformation.Amount.InstructedAmount.Currency {transferId} | D11: ActiveCurrencyAndAmount | E11: Amount of money moved between the instructing agent and the instructed agent. | F11: Enriched from Quote via TransferID
A12: FIToFICustomerCreditTransferV10.CreditTransferTransactionInformation.ChargeBearer | C12: DEBT | D12: ChargeBearerTypeCode | E12: Specifies which party(ies) will pay charges due for processing of the instruction.
A13: FIToFICustomerCreditTransferV10.CreditTransferTransactionInformation.Charges[1].Amount.Amount | C13: ='pain.001.001.11'!A47 & " {" & Comparison!$F$5 & "}" -> CustomerCreditTransferInitiationV11.PaymentInformation.CreditTransferTransactionInformation.SupplementaryData.Envelope.Document.PayerFspFees.Amount {transferId} | D13: ActiveCurrencyAndAmount | E13: Transaction charges to be paid by the charge bearer. | F13: Enriched from Quote via TransferID
A14: FIToFICustomerCreditTransferV10.CreditTransferTransactionInformation.Charges[1].Amount.Currency | C14: ='pain.001.001.11'!A48 & " {" & Comparison!$F$5 & "}" -> CustomerCreditTransferInitiationV11.PaymentInformation.CreditTransferTransactionInformation.SupplementaryData.Envelope.Document.PayerFspFees.Currency {transferId} | D14: ActiveCurrencyAndAmount | E14: Transaction charges to be paid by the charge bearer. | F14: Enriched from Quote via TransferID
A15: FIToFICustomerCreditTransferV10.CreditTransferTransactionInformation.Charges[1].Agent.FinancialInstitutionIdentification.ClearingSystemMemberIdentification.MemberIdentification | C15: =Comparison!F30 -> payerFsp | D15: Max35Text | E15: Agent that takes the transaction charges or to which the transaction charges are due. | F15: Fees to the Payer FSP by the Payer
A16: FIToFICustomerCreditTransferV10.CreditTransferTransactionInformation.Charges[2].Amount.Amount | C16: ='pain.001.013.09'!A47 -> CreditorPaymentActivationRequestV09.PaymentInformation.CreditTransferTransactionInformation.SupplementaryData.Envelope.Document.PayeeFspFee.Amount | D16: ActiveCurrencyAndAmount | E16: Transaction charges to be paid by the charge bearer. | F16: Enriched from Quote via TransferID
A17: FIToFICustomerCreditTransferV10.CreditTransferTransactionInformation.Charges[2].Amount.Currency | C17: ='pain.001.013.09'!A48 -> CreditorPaymentActivationRequestV09.PaymentInformation.CreditTransferTransactionInformation.SupplementaryData.Envelope.Document.PayeeFspFee.Currency | D17: ActiveCurrencyAndAmount | E17: Transaction charges to be paid by the charge bearer. | F17: Enriched from Quote via TransferID
A18: FIToFICustomerCreditTransferV10.CreditTransferTransactionInformation.Charges[2].Agent.FinancialInstitutionIdentification.ClearingSystemMemberIdentification.MemberIdentification | C18: =Comparison!F12 -> payeeFsp | D18: Max35Text | E18: Agent that takes the transaction charges or to which the transaction charges are due. | F18: Fees to the Payee FSP by the Payer
A19: FIToFICustomerCreditTransferV10.CreditTransferTransactionInformation.Charges[3].Amount.Amount | C19: ='pain.001.013.09'!A49 -> CreditorPaymentActivationRequestV09.PaymentInformation.CreditTransferTransactionInformation.SupplementaryData.Envelope.Document.PayeeFspCommission.Amount | D19: ActiveCurrencyAndAmount | E19: Transaction charges to be paid by the charge bearer. | F19: Enriched from Quote via TransferID
A20: FIToFICustomerCreditTransferV10.CreditTransferTransactionInformation.Charges[3].Amount.Currency | C20: ='pain.001.013.09'!A50 -> CreditorPaymentActivationRequestV09.PaymentInformation.CreditTransferTransactionInformation.SupplementaryData.Envelope.Document.PayeeFspCommission.Currency | D20: ActiveCurrencyAndAmount | E20: Transaction charges to be paid by the charge bearer. | F20: Enriched from Quote via TransferID
A21: FIToFICustomerCreditTransferV10.CreditTransferTransactionInformation.Charges[3].Agent.FinancialInstitutionIdentification.ClearingSystemMemberIdentification.MemberIdentification | C21: =Comparison!F12 -> payeeFsp | D21: Max35Text | E21: Agent that takes the transaction charges or to which the transaction charges are due. | F21: Payee FSP commission to the Payer FSP by the Payer - Unsure if this is paid by the Payer as part of the total amount or the Payee FSP as a separate amount - TBC
A22: FIToFICustomerCreditTransferV10.CreditTransferTransactionInformation.InitiatingParty.Name | C22: ='pain.001.013.09'!A5 & " {" & Comparison!$F$5 & "}" -> CreditorPaymentActivationRequestV09.GroupHeader.InitiatingParty.Name {transferId} | D22: Max140Text | E22: Name by which a party is known and which is usually used to identify that party. | F22: Enriched from Quote via TransferID
A23: FIToFICustomerCreditTransferV10.CreditTransferTransactionInformation.InitiatingParty.Identification.PrivateIdentification.DateAndPlaceOfBirth.BirthDate | C23: ='pain.001.013.09'!A6 & " {" & Comparison!$F$5 & "}" -> CreditorPaymentActivationRequestV09.GroupHeader.InitiatingParty.Identification.PrivateIdentification.DateAndPlaceOfBirth.BirthDate {transferId} | D23: ISODate | E23: Unique and unambiguous identification of a party. | F23: Enriched from Quote via TransferID
A24: FIToFICustomerCreditTransferV10.CreditTransferTransactionInformation.InitiatingParty.Identification.PrivateIdentification.Other.Identification | C24: ='pain.001.013.09'!A7 & " {" & Comparison!$F$5 & "}" -> CreditorPaymentActivationRequestV09.GroupHeader.InitiatingParty.Identification.PrivateIdentification.Other.Identification {transferId} | D24: Max35Text | E24: Unique and unambiguous identification of a person. | F24: Enriched from Quote via TransferID
A25: FIToFICustomerCreditTransferV10.CreditTransferTransactionInformation.InitiatingParty.Identification.PrivateIdentification.Other.SchemeName.Proprietary | C25: ='pain.001.013.09'!A8 & " {" & Comparison!$F$5 & "}" -> CreditorPaymentActivationRequestV09.GroupHeader.InitiatingParty.Identification.PrivateIdentification.Other.SchemeName.Proprietary {transferId} | D25: Max35Text | E25: Name of the identification scheme, in a free text form. | F25: Enriched from Quote via TransferID
A26: FIToFICustomerCreditTransferV10.CreditTransferTransactionInformation.InitiatingParty.ContactDetails.MobileNumber | C26: ='pain.001.013.09'!A9 & " {" & Comparison!$F$5 & "}" -> CreditorPaymentActivationRequestV09.GroupHeader.InitiatingParty.ContactDetails.MobileNumber {transferId} | D26: PhoneNumber | E26: Collection of information that identifies a mobile phone number, as defined by telecom services. | F26: Enriched from Quote via TransferID
A27: FIToFICustomerCreditTransferV10.CreditTransferTransactionInformation.Debtor.Name | C27: ='pain.001.013.09'!A15 & " {" & Comparison!$F$5 & "}" -> CreditorPaymentActivationRequestV09.PaymentInformation.Debtor.Name {transferId} | D27: Max140Text | E27: Name by which a party is known and which is usually used to identify that party. | F27: Enriched from Quote via TransferID
A28: FIToFICustomerCreditTransferV10.CreditTransferTransactionInformation.Debtor.Identification.PrivateIdentification.DateAndPlaceOfBirth.BirthDate | C28: ='pain.001.013.09'!A16 & " {" & Comparison!$F$5 & "}" -> CreditorPaymentActivationRequestV09.PaymentInformation.Debtor.Identification.PrivateIdentification.DateAndPlaceOfBirth.BirthDate {transferId} | D28: ISODate | E28: Unique and unambiguous identification of a party. | F28: Enriched from Quote via TransferID
A29: FIToFICustomerCreditTransferV10.CreditTransferTransactionInformation.Debtor.Identification.PrivateIdentification.Other.Identification | C29: ='pain.001.013.09'!A17 & " {" & Comparison!$F$5 & "}" -> CreditorPaymentActivationRequestV09.PaymentInformation.Debtor.Identification.PrivateIdentification.Other.Identification {transferId} | D29: Max35Text | E29: Unique and unambiguous identification of a person. | F29: Enriched from Quote via TransferID
A30: FIToFICustomerCreditTransferV10.CreditTransferTransactionInformation.Debtor.Identification.PrivateIdentification.Other.SchemeName.Proprietary | C30: ='pain.001.013.09'!A18 & " {" & Comparison!$F$5 & "}" -> CreditorPaymentActivationRequestV09.PaymentInformation.Debtor.Identification.PrivateIdentification.Other.SchemeName.Proprietary {transferId} | D30: Max35Text | E30: Name of the identification scheme, in a free text form. | F30: Enriched from Quote via TransferID
A31: FIToFICustomerCreditTransferV10.CreditTransferTransactionInformation.Debtor.ContactDetails.MobileNumber | C31: ='pain.001.013.09'!A19 & " {" & Comparison!$F$5 & "}" -> CreditorPaymentActivationRequestV09.PaymentInformation.Debtor.ContactDetails.MobileNumber {transferId} | D31: PhoneNumber | E31: Collection of information that identifies a mobile phone number, as defined by telecom services. | F31: Enriched from Quote via TransferID
A32: FIToFICustomerCreditTransferV10.CreditTransferTransactionInformation.DebtorAccount.Identification.Other.Identification | C32: ='pain.001.013.09'!A20 & " {" & Comparison!$F$5 & "}" -> CreditorPaymentActivationRequestV09.PaymentInformation.DebtorAccount.Identification.Other.Identification {transferId} | D32: Max34Text | E32: Identification assigned by an institution. | F32: Enriched from Quote via TransferID
A33: FIToFICustomerCreditTransferV10.CreditTransferTransactionInformation.DebtorAccount.Identification.Other.Identification.SchemeName.Proprietary | C33: ='pain.001.013.09'!A21 & " {" & Comparison!$F$5 & "}" -> CreditorPaymentActivationRequestV09.PaymentInformation.DebtorAccount.Identification.Other.Identification.SchemeName.Proprietary {transferId} | D33: Max35Text | E33: Name of the identification scheme, in a free text form. | F33: Enriched from Quote via TransferID
A34: FIToFICustomerCreditTransferV10.CreditTransferTransactionInformation.DebtorAccount.Name | C34: ='pain.001.013.09'!A22 & " {" & Comparison!$F$5 & "}" -> CreditorPaymentActivationRequestV09.PaymentInformation.DebtorAccount.Name {transferId} | D34: Max70Text | E34: Name of the account, as assigned by the account servicing institution, in agreement with the account owner in order to provide an additional means of identification of the account. Usage: The account name is different from the account owner name. The account name is used in certain user communities to provide a means of identifying the account, in addition to the account owner's identity and the account number. | F34: Enriched from Quote via TransferID
A35: FIToFICustomerCreditTransferV10.CreditTransferTransactionInformation.DebtorAgent.FinancialInstitutionIdentification.ClearingSystemMemberIdentification.MemberIdentification | C35: =Comparison!F30 -> payerFsp | D35: Max35Text | E35: Identification of a member of a clearing system. | F35: Enriched from Quote via TransferID
A36: FIToFICustomerCreditTransferV10.CreditTransferTransactionInformation.CreditorAgent.FinancialInstitutionIdentification.ClearingSystemMemberIdentification.MemberIdentification | C36: =Comparison!F12 -> payeeFsp | D36: Max35Text | E36: Identification of a member of a clearing system. | F36: Enriched from Quote via TransferID
A37: FIToFICustomerCreditTransferV10.CreditTransferTransactionInformation.Creditor.Name | C37: ='pain.001.013.09'!A33 & " {" & Comparison!$F$5 & "}" -> CreditorPaymentActivationRequestV09.PaymentInformation.CreditTransferTransactionInformation.Creditor.Name {transferId} | D37: Max140Text | E37: Name by which a party is known and which is usually used to identify that party. | F37: Enriched from Quote via TransferID
A38: FIToFICustomerCreditTransferV10.CreditTransferTransactionInformation.Creditor.Identification.PrivateIdentification.DateAndPlaceOfBirth.BirthDate | C38: ='pain.001.013.09'!A34 & " {" & Comparison!$F$5 & "}" -> CreditorPaymentActivationRequestV09.PaymentInformation.CreditTransferTransactionInformation.Creditor.Identification.PrivateIdentification.DateAndPlaceOfBirth.BirthDate {transferId} | D38: ISODate | E38: Unique and unambiguous identification of a party. | F38: Enriched from Quote via TransferID
A39: FIToFICustomerCreditTransferV10.CreditTransferTransactionInformation.Creditor.Identification.PrivateIdentification.Other.Identification | C39: ='pain.001.013.09'!A35 & " {" & Comparison!$F$5 & "}" -> CreditorPaymentActivationRequestV09.PaymentInformation.CreditTransferTransactionInformation.Creditor.Identification.PrivateIdentification.Other.Identification {transferId} | D39: Max35Text | E39: Unique and unambiguous identification of a person. | F39: Enriched from Quote via TransferID
A40: FIToFICustomerCreditTransferV10.CreditTransferTransactionInformation.Creditor.Identification.PrivateIdentification.Other.SchemeName.Proprietary | C40: ='pain.001.013.09'!A36 & " {" & Comparison!$F$5 & "}" -> CreditorPaymentActivationRequestV09.PaymentInformation.CreditTransferTransactionInformation.Creditor.Identification.PrivateIdentification.Other.SchemeName.Proprietary {transferId} | D40: Max35Text | E40: Name of the identification scheme, in a free text form. | F40: Enriched from Quote via TransferID
A41: FIToFICustomerCreditTransferV10.CreditTransferTransactionInformation.Creditor.ContactDetails.MobileNumber | C41: ='pain.001.013.09'!A37 & " {" & Comparison!$F$5 & "}" -> CreditorPaymentActivationRequestV09.PaymentInformation.CreditTransferTransactionInformation.Creditor.ContactDetails.MobileNumber {transferId} | D41: PhoneNumber | E41: Collection of information that identifies a mobile phone number, as defined by telecom services. | F41: Enriched from Quote via TransferID
A42: FIToFICustomerCreditTransferV10.CreditTransferTransactionInformation.CreditorAccount.Identification.Other.Identification | C42: ='pain.001.013.09'!A38 & " {" & Comparison!$F$5 & "}" -> CreditorPaymentActivationRequestV09.PaymentInformation.CreditTransferTransactionInformation.CreditorAccount.Identification.Other.Identification {transferId} | D42: Max34Text | E42: Identification assigned by an institution. | F42: Enriched from Quote via TransferID
A43: FIToFICustomerCreditTransferV10.CreditTransferTransactionInformation.CreditorAccount.Identification.Other.Identification.SchemeName.Proprietary | C43: ='pain.001.013.09'!A39 & " {" & Comparison!$F$5 & "}" -> CreditorPaymentActivationRequestV09.PaymentInformation.CreditTransferTransactionInformation.CreditorAccount.Identification.Other.Identification.SchemeName.Proprietary {transferId} | D43: Max35Text | E43: Name of the identification scheme, in a free text form. | F43: Enriched from Quote via TransferID
A44: FIToFICustomerCreditTransferV10.CreditTransferTransactionInformation.CreditorAccount.Name | C44: ='pain.001.013.09'!A40 & " {" & Comparison!$F$5 & "}" -> CreditorPaymentActivationRequestV09.PaymentInformation.CreditTransferTransactionInformation.CreditorAccount.Name {transferId} | D44: Max70Text | E44: Name of the account, as assigned by the account servicing institution, in agreement with the account owner in order to provide an additional means of identification of the account. Usage: The account name is different from the account owner name. The account name is used in certain user communities to provide a means of identifying the account, in addition to the account owner's identity and the account number. | F44: Enriched from Quote via TransferID
A45: FIToFICustomerCreditTransferV10.CreditTransferTransactionInformation.Purpose.Code | C45: ='pain.001.013.09'!A41 & " {" & Comparison!$F$5 & "}" -> CreditorPaymentActivationRequestV09.PaymentInformation.CreditTransferTransactionInformation.Purpose.Code {transferId} | D45: ExternalPurpose1Code | E45: Underlying reason for the payment transaction, as published in an external purpose code list. | F45: This code denotes a Mobile Person-to-Person payment, which is the pre-dominant use of Mojaloop. Merchant payments will be introduced at some point and some logic will be required to identify whether this code is MP2P or MP2B.
A46: CustomerCreditTransferInitiation.CreditTransferTransactionInformation.RegulatoryReporting.DebitCreditReportingIndicator | C46: ='pain.001.013.09'!A42 & " {" & Comparison!$F$5 & "}" -> CustomerCreditTransferInitiation.PaymentInformation.CreditTransferTransactionInformation.RegulatoryReporting.DebitCreditReportingIndicator {transferId} | D46: RegulatoryReportingType1Code | E46: Identifies whether the regulatory reporting information applies to the debit side, to the credit side or to both debit and credit sides of the transaction. | F46: Enriched from Quote via TransferID
A47: CustomerCreditTransferInitiation.CreditTransferTransactionInformation.RegulatoryReporting.Details.Type | C47: ='pain.001.013.09'!A43 & " {" & Comparison!$F$5 & "}" -> CustomerCreditTransferInitiation.PaymentInformation.CreditTransferTransactionInformation.RegulatoryReporting.Details.Type {transferId} | D47: Max35Text | E47: Specifies the type of the information supplied in the regulatory reporting details. | F47: Enriched from Quote via TransferID
A48: CustomerCreditTransferInitiation.CreditTransferTransactionInformation.RegulatoryReporting.Details.Code | C48: ='pain.001.013.09'!A44 & " {" & Comparison!$F$5 & "}" -> CustomerCreditTransferInitiation.PaymentInformation.CreditTransferTransactionInformation.RegulatoryReporting.Details.Code {transferId} | D48: Max10Text | E48: Specifies the nature, purpose, and reason for the transaction to be reported for regulatory and statutory requirements in a coded form. | F48: Enriched from Quote via TransferID
A49: CustomerCreditTransferInitiation.CreditTransferTransaction.RemittanceInformation.Unstructured | C49: ='pain.001.001.11'!A44 & " {" & Comparison!$F$5 & "}" -> CustomerCreditTransferInitiation.PaymentInformation.CreditTransferTransaction.RemittanceInformation.Unstructured {transferId} | D49: Max140Text | E49: Information supplied to enable the matching/reconciliation of an entry with the items that the payment is intended to settle, such as commercial invoices in an accounts' receivable system, in an unstructured form. | F49: Enriched from Quote via TransferID
A50: FIToFICustomerCreditTransferV10.CreditTransferTransactionInformation.SupplementaryData.Envelope.Document.Expiration | C50: =Comparison!F75 -> expiration

Sheet pacs.002.001.12
A1: ISO20022 data element | B1: Xpath | C1: Value | D1: Type | E1: Description | F1: Notes
A2: FIToFIPaymentStatusReportV12.GroupHeader.MessageIdentification | B2: Document.CstmrCdtTrfInitn.GrpHdr.MsgId | C2: Generate fresh UUID | D2: Max35Text | E2: Point to point reference, as assigned by the instructing party, and sent to the next party in the chain to unambiguously identify the message.
A3: FIToFIPaymentStatusReportV12.GroupHeader.CreationDateTime | B3: Document.CstmrCdtTrfInitn.GrpHdr.CreDtTm | C3: Timestamp at the time the message is received by the TMS API | D3: ISODateTime | E3: Date and time at which the message was created.
A4: FIToFIPaymentStatusReportV12.GroupHeader.OriginalBusinessQuery.MessageIdentification | B4: Document.CstmrCdtTrfInitn.GrpHdr.NbOfTxs | C4: =Comparison!H5 -> transferId (from URI) | D4: Max35Text | E4: Point to point reference, as assigned by the original initiating party, to unambiguously identify the original query message. | F4: Retrieved from incoming message URI
A5: FIToFIPaymentStatusReportV12.GroupHeader.OriginalBusinessQuery.CreationDateTime | C5: ='pacs.008.001.10'!A3 & " {" & C4 & "}" -> FIToFICustomerCreditTransferV10.GroupHeader.CreationDateTime {transferId (from URI)} | D5: ISODateTime | E5: Date and time at which the original message was created. | F5: Enriched from Transfer via TransferID
A6: FIToFIPaymentStatusReportV12.TransactionInformationAndStatus.OriginalInstructionIdentification | C6: ='pain.001.001.11'!A10 & " {" & C4 & "}" -> CustomerCreditTransferInitiationV11.PaymentInformation.PaymentInformationIdentification {transferId (from URI)} | D6: Max35Text | E6: Unique identification, as assigned by an instructing party for an instructed party, to unambiguously identify the instruction. Usage: The instruction identification is a point to point reference that can be used between the instructing party and the instructed party to refer to the individual instruction. It can be included in several messages related to the instruction. | F6: Enriched from Quote via TransferID
A7: FIToFIPaymentStatusReportV12.TransactionInformationAndStatus.OriginalEndtoEndIdentification | C7: =Comparison!H5 -> transferId (from URI) | D7: Max35Text | E7: Unique identification assigned by the initiating party to unambiguously identify the transaction. This identification is passed on, unchanged, throughout the entire end-to-end chain. Usage: The end-to-end identification can be used for reconciliation or to link tasks relating to the transaction. It can be included in several messages related to the transaction. | F7: Retrieved from incoming message URI
A8: FIToFIPaymentStatusReportV12.TransactionInformationAndStatus.TransactionStatus | C8: ="IF " & Comparison!H78 & " = 'RECEIVED' THEN 'RCVD'; ='RESERVED' THEN 'ACSC'; ='COMMITTED' THEN 'ACCC'; ='ABORTED' THEN 'RJCT'" -> IF transferState = 'RECEIVED' THEN 'RCVD'; ='RESERVED' THEN 'ACSC'; ='COMMITTED' THEN 'ACCC'; ='ABORTED' THEN 'RJCT' | D8: ExternalPaymentTransactionStatusCode | E8: Specifies the status of an individual payment instructions, as published in an external payment transaction status code set. External code sets can be downloaded from www.iso20022.org. minLength: 1 maxLength: 4 | F8: Mapped from Mojaloop statuses to ISO statuses.
A9: FIToFIPaymentStatusReportV12.TransactionInformationAndStatus.AcceptanceDateTime | C9: =Comparison!H77 -> completedTimestamp | D9: ISODateTime | E9: Point in time when the payment order from the initiating party meets the processing conditions of the account servicing agent. This means that the account servicing agent has received the payment order and has applied checks such as authorisation, availability of funds.
A10: FIToFIPaymentStatusReportV12.TransactionInformationAndStatus.Charges[1].Amount.Amount | C10: ='pain.001.001.11'!A47 & " {" & Comparison!$F$5 & "}" -> CustomerCreditTransferInitiationV11.PaymentInformation.CreditTransferTransactionInformation.SupplementaryData.Envelope.Document.PayerFspFees.Amount {transferId} | D10: ActiveCurrencyAndAmount | E10: Transaction charges to be paid by the charge bearer.
A11: FIToFIPaymentStatusReportV12.TransactionInformationAndStatus.Charges[1].Amount.Currency | C11: ='pain.001.001.11'!A48 & " {" & Comparison!$F$5 & "}" -> CustomerCreditTransferInitiationV11.PaymentInformation.CreditTransferTransactionInformation.SupplementaryData.Envelope.Document.PayerFspFees.Currency {transferId} | D11: ActiveCurrencyAndAmount | E11: Transaction charges to be paid by the charge bearer.
A12: FIToFIPaymentStatusReportV12.TransactionInformationAndStatus.Charges[1].Agent.FinancialInstitutionIdentification.ClearingSystemMemberIdentification.MemberIdentification | C12: ='pacs.008.001.10'!A35 & " {" & $C$4 & "}" -> FIToFICustomerCreditTransferV10.CreditTransferTransactionInformation.DebtorAgent.FinancialInstitutionIdentification.ClearingSystemMemberIdentification.MemberIdentification {transferId (from URI)} | D12: Max35Text | E12: Agent that takes the transaction charges or to which the transaction charges are due.
A13: FIToFIPaymentStatusReportV12.TransactionInformationAndStatus.Charges[2].Amount.Amount | C13: ='pain.001.013.09'!A47 -> CreditorPaymentActivationRequestV09.PaymentInformation.CreditTransferTransactionInformation.SupplementaryData.Envelope.Document.PayeeFspFee.Amount | D13: ActiveCurrencyAndAmount | E13: Transaction charges to be paid by the charge bearer.
A14: FIToFIPaymentStatusReportV12.TransactionInformationAndStatus.Charges[2].Amount.Currency | C14: ='pain.001.013.09'!A48 -> CreditorPaymentActivationRequestV09.PaymentInformation.CreditTransferTransactionInformation.SupplementaryData.Envelope.Document.PayeeFspFee.Currency | D14: ActiveCurrencyAndAmount | E14: Transaction charges to be paid by the charge bearer.
A15: FIToFIPaymentStatusReportV12.TransactionInformationAndStatus.Charges[2].Agent.FinancialInstitutionIdentification.ClearingSystemMemberIdentification.MemberIdentification | C15: ='pacs.008.001.10'!A36 & " {" & $C$4 & "}" -> FIToFICustomerCreditTransferV10.CreditTransferTransactionInformation.CreditorAgent.FinancialInstitutionIdentification.ClearingSystemMemberIdentification.MemberIdentification {transferId (from URI)} | D15: Max35Text | E15: Agent that takes the transaction charges or to which the transaction charges are due.
A16: FIToFIPaymentStatusReportV12.TransactionInformationAndStatus.Charges[3].Amount.Amount | C16: ='pain.001.013.09'!A49 -> CreditorPaymentActivationRequestV09.PaymentInformation.CreditTransferTransactionInformation.SupplementaryData.Envelope.Document.PayeeFspCommission.Amount | D16: ActiveCurrencyAndAmount | E16: Transaction charges to be paid by the charge bearer.
A17: FIToFIPaymentStatusReportV12.TransactionInformationAndStatus.Charges[3].Amount.Currency | C17: ='pain.001.013.09'!A50 -> CreditorPaymentActivationRequestV09.PaymentInformation.CreditTransferTransactionInformation.SupplementaryData.Envelope.Document.PayeeFspCommission.Currency | D17: ActiveCurrencyAndAmount | E17: Transaction charges to be paid by the charge bearer.
A18: FIToFIPaymentStatusReportV12.TransactionInformationAndStatus.Charges[3].Agent.FinancialInstitutionIdentification.ClearingSystemMemberIdentification.MemberIdentification | C18: ='pacs.008.001.10'!A36 & " {" & $C$4 & "}" -> FIToFICustomerCreditTransferV10.CreditTransferTransactionInformation.CreditorAgent.FinancialInstitutionIdentification.ClearingSystemMemberIdentification.MemberIdentification {transferId (from URI)} | D18: Max35Text | E18: Agent that takes the transaction charges or to which the transaction charges are due.
A19: FIToFIPaymentStatusReportV12.TransactionInformationAndStatus.InstructingAgent.FinancialInstitutionIdentification.ClearingSystemMemberIdentification.MemberIdentification | C19: ='pacs.008.001.10'!A35 & " {" & $C$4 & "}" -> FIToFICustomerCreditTransferV10.CreditTransferTransactionInformation.DebtorAgent.FinancialInstitutionIdentification.ClearingSystemMemberIdentification.MemberIdentification {transferId (from URI)} | D19: Max35Text | E19: Identification of a member of a clearing system.
A20: FIToFIPaymentStatusReportV12.TransactionInformationAndStatus.InstructedAgent.FinancialInstitutionIdentification.ClearingSystemMemberIdentification.MemberIdentification | C20: ='pacs.008.001.10'!A36 & " {" & $C$4 & "}" -> FIToFICustomerCreditTransferV10.CreditTransferTransactionInformation.CreditorAgent.FinancialInstitutionIdentification.ClearingSystemMemberIdentification.MemberIdentification {transferId (from URI)} | D20: Max35Text | E20: Identification of a member of a clearing system.

Sheet POST quotes
A1: Mapping Mojaloop's POST /quotes message onto ISO 20022 pain.001
A3: This mapping describes how an incoming pain.001 message (shown in column C) can be mapped onto the data elements of the Mojaloop POST /quotes message (shown in column A). Where default values are to be applied, they are shown in Column B. This mapping assumes that only phone numbers will be used as identifiers.
A5: Moja | B5: Default | C5: BusinessComponent | D5: JSON Path | E5: Description | F5: Field/Collection | G5: Action | H5: Element | I5: ISO pain.001 XSD reference | J5: Data Dictionary Reference | K5: Comment
A6: quoteId | D6: quoteId | E6: Common ID between the FSPs for the quote object, decided by the Payer FSP. The ID should be reused for resends of the same quote for a transaction. A new ID should be generated for each new quote for a transaction. | F6: Field | G6: Map | H6: CustomerCreditTransferInitiation.PaymentInformation.PaymentInformationIdentification | I6: Document.CstmrCdtTrfInitn.PmtInf.PmtInfId | J6: https://www.iso20022.org/standardsrepository/type/PaymentInstruction34
A7: transactionId | D7: transactionId | E7: Common ID (decided by the Payer FSP) between the FSPs for the future transaction object. The actual transaction will be created as part of a successful transfer process. The ID should be reused for resends of the same quote for a transaction. A new ID should be generated for each new quote for a transaction. | F7: Field | G7: Map | H7: CustomerCreditTransferInitiation.PaymentInformation.CreditTransferTransactionInformation.PaymentIdentification.EndToEndIdentification | I7: Document.CstmrCdtTrfInitn.PmtInf.CdtTrfTxInf.PmtId.EndToEndId | J7: https://www.iso20022.org/standardsrepository/type/PaymentIdentification6
A8: transactionRequestId | B8: omit | D8: transactionRequestId | E8: Identifies an optional previously-sent transaction request. | F8: Field | G8: Discard | K8: This field is used by Mojaloop to manage repeat requests of the same message.
A9: payee | D9: payee | E9: Information about the Payee in the proposed financial transaction. | F9: Collection
A10: partyIdInfo | D10: payee.partyIdInfo | E10: Party Id type, id, sub ID or type, and FSP Id. | F10: Collection
A11: partyIdType | B11: MSISDN | D11: payee.partyIdInfo.partyIdType | E11: The type of the identifier. | F11: Field | G11: Map | H11: CustomerCreditTransferInitiation.PaymentInformation.CreditTransferTransaction.CreditorAccount.Identification.Other.Identification.SchemeName.Proprietary | J11: https://www.iso20022.org/standardsrepository/type/AccountSchemeName1Choice | K11: This should be MSISDN, usually, but may be another classification of the account number
A12: partyIdentifier | D12: payee.partyIdInfo.partyIdentifier | E12: An identifier for the Party. | F12: Field | G12: Map | H12: CustomerCreditTransferInitiation.PaymentInformation.CreditTransferTransaction.CreditorAccount.Identification.Other.Identification | J12: https://www.iso20022.org/standardsrepository/type/GenericAccountIdentification1 | K12: This is the account the initiator said they wanted to pay.
A13: partySubIdOrType | B13: omit | D13: payee.partyIdInfo.partySubIdOrType | E13: A sub-identifier or sub-type for the Party. | F13: Field | G13: Discard | K13: This field is for KYC purposes and can be ignored for now
A14: fspId | D14: payee.partyIdInfo.fspId | E14: The FSP identifier. | F14: Field | G14: Map | H14: CustomerCreditTransferInitiation.PaymentInformation.CreditTransferTransaction.CreditorAgent.FinancialInstitutionIdentification.ClearingSystemMemberIdentification.MemberIdentification | J14: https://www.iso20022.org/standardsrepository/type/ClearingSystemMemberIdentification2 | K14: The participants of the scheme should be idetifiable to the scheme through the scheme's naming rules
A15: extensionList | B15: omit | D15: payee.partyIdInfo.extensionList | E15: Optional list of extensions to the payee information, specific to deployment. | F15: Collection
A16: extension | D16: payee.partyIdInfo.extensionList.extension | E16: An optional extension element defined by a key-value pair
A17: key | D17: payee.partyIdInfo.extensionList.extension.key | E17: The key for an optional extension element value
A18: value | D18: payee.partyIdInfo.extensionList.extension.value | E18: The value for an optional extension element key
A19: merchantClassificationCode | B19: omit | D19: payee.merchantClassificationCode | E19: A limited set of pre-defined numbers. This list would be a limited set of numbers identifying a set of popular merchant types like School Fees, Pubs and Restaurants, Groceries, and so on. | F19: Field | G19: Map | H19: CustomerCreditTransferInitiation.SupplementaryData | J19: https://www.iso20022.org/standardsrepository/type/CustomerCreditTransferInitiationV10 | K19: pain.001 doesn't accommodate this message, but we would need it. It should be added to SupplementaryData
A20: name | B20: omit | D20: payee.name | E20: The name of the party, could be a real name or a nick name. | F20: Field | G20: Map | H20: CustomerCreditTransferInitiation.PaymentInformation.CreditTransferTransactionInformation.CreditorAccount.Proxy | J20: https://www.iso20022.org/standardsrepository/type/PartyIdentification135 | K20: This name field does not necessarily relate to the name of the account holder.
A21: personalInfo | D21: payee.personalInfo | E21: Personal information used to verify identity of Party such as first, middle, last name and date of birth. | F21: Collection
A22: complexName | D22: payee.personalInfo.complexName | E22: First, middle and last name. | F22: Collection | K22: We don't know this yet…
A23: firstName | B23: omit | D23: payee.personalInfo.complexName.firstName | E23: First name | F23: Field | G23: Map | H23: CustomerCreditTransferInitiation.PaymentInformation.CreditTransferTransaction.Creditor.Name | J23: https://www.iso20022.org/standardsrepository/type/PartyIdentification135 | K23: Concatenate the 3-part name into one field
A24: middleName | B24: omit | D24: payee.personalInfo.complexName.middleName | E24: Middle name | F24: Field | G24: Map | H24: CustomerCreditTransferInitiation.PaymentInformation.CreditTransferTransaction.Creditor.Name | J24: https://www.iso20022.org/standardsrepository/type/PartyIdentification135 | K24: Concatenate the 3-part name into one field
A25: lastName | B25: omit | D25: payee.personalInfo.complexName.lastName | E25: Last name | F25: Field | G25: Map | H25: CustomerCreditTransferInitiation.PaymentInformation.CreditTransferTransaction.Creditor.Name | J25: https://www.iso20022.org/standardsrepository/type/PartyIdentification135 | K25: Concatenate the 3-part name into one field
A26: dateOfBirth | B26: omit | D26: payee.personalInfo.dateOfBirth | E26: Date of birth | F26: Field | G26: Map | H26: CustomerCreditTransferInitiation.PaymentInformation.CreditTransferTransaction.Creditor.Identification.PrivateIdentification.DateAndPlaceOfBirth.Birthdate | J26: https://www.iso20022.org/standardsrepository/type/DateAndPlaceOfBirth1 | K26: Format date into ISODate format
A27: payer | D27: payer | E27: Information about the Payer in the proposed financial transaction. | F27: Collection
A28: partyIdInfo | D28: payer.partyIdInfo | E28: Party Id type, id, sub ID or type, and FSP Id. | F28: Collection
A29: partyIdType | B29: MSISDN | D29: payer.partyIdInfo.partyIdType | E29: The type of the identifier. | F29: Field | G29: Map | H29: CustomerCreditTransferInitiation.PaymentInformation.DebtorAccount.Identification.Other.Identification.SchemeName.Proprietary | J29: https://www.iso20022.org/standardsrepository/type/AccountSchemeName1Choice | K29: This should be MSISDN, usually, but may be another classification of the account number
A30: partyIdentifier | D30: payer.partyIdInfo.partyIdentifier | E30: An identifier for the Party. | F30: Field | G30: Map | H30: CustomerCreditTransferInitiation.PaymentInformation.DebtorAccount.Identification.Other | J30: https://www.iso20022.org/standardsrepository/type/GenericAccountIdentification1 | K30: This is the identifier of the account of the payer
A31: partySubIdOrType | B31: omit | D31: payer.partyIdInfo.partySubIdOrType | E31: A sub-identifier or sub-type for the Party. | F31: Field | G31: Discard | K31: This field is for KYC purposes and can be ignored for now
A32: fspId | D32: payer.partyIdInfo.fspId | E32: The FSP identifier. | F32: Field | G32: Map | H32: CustomerCreditTransferInitiation.PaymentInformation.DebtorAgent.FinancialInstitutionIdentification.ClearingSystemMemberIdentification.MemberIdentification | J32: https://www.iso20022.org/standardsrepository/type/ClearingSystemMemberIdentification2 | K32: The participants of the scheme should be idetifiable to the scheme through the scheme's naming rules
A33: extensionList | B33: omit | D33: payer.partyIdInfo.extensionList | E33: Optional list of extensions to the payer information, specific to deployment. | F33: Collection
A34: extension | D34: payer.partyIdInfo.extensionList.extension | E34: An optional extension element defined by a key-value pair
A35: key | D35: payer.partyIdInfo.extensionList.extension.key | E35: The key for an optional extension element value
A36: value | D36: payer.partyIdInfo.extensionList.extension.value | E36: The value for an optional extension element key
A37: merchantClassificationCode | B37: omit | D37: payer.merchantClassificationCode | E37: A limited set of pre-defined numbers. This list would be a limited set of numbers identifying a set of popular merchant types like School Fees, Pubs and Restaurants, Groceries, and so on. | F37: Field | G37: Map | H37: CustomerCreditTransferInitiation.SupplementaryData | J37: https://www.iso20022.org/standardsrepository/type/CustomerCreditTransferInitiationV10 | K37: pain.001 doesn't accommodate this message, but we would need it. It should be added to SupplementaryData
A38: name | B38: omit | D38: payer.name | E38: The name of the party, could be a real name or a nick name. | F38: Field | G38: Map | H38: CustomerCreditTransferInitiation.PaymentInformation.DebtorAccount.Proxy | J38: https://www.iso20022.org/standardsrepository/type/PartyIdentification135 | K38: This name field does not necessarily relate to the name of the account holder.
A39: personalInfo | B39: omit | D39: payer.personalInfo | E39: Personal information used to verify identity of Party such as first, middle, last name and date of birth. | F39: Collection
A40: complexName | B40: omit | D40: payer.personalInfo.complexName | E40: First, middle and last name. | F40: Collection
A41: firstName | B41: omit | D41: payer.personalInfo.complexName.firstName | E41: First name | F41: Field | G41: Map | H41: CustomerCreditTransferInitiation.PaymentInformation.Debtor.Name | J41: https://www.iso20022.org/standardsrepository/type/PartyIdentification135 | K41: Concatenate the 3-part name into one field
A42: middleName | B42: omit | D42: payer.personalInfo.complexName.middleName | E42: Middle name | F42: Field | G42: Map | H42: CustomerCreditTransferInitiation.PaymentInformation.Debtor.Name | J42: https://www.iso20022.org/standardsrepository/type/PartyIdentification135 | K42: Concatenate the 3-part name into one field
A43: lastName | B43: omit | D43: payer.personalInfo.complexName.lastName | E43: Last name | F43: Field | G43: Map | H43: CustomerCreditTransferInitiation.PaymentInformation.Debtor.Name | J43: https://www.iso20022.org/standardsrepository/type/PartyIdentification135 | K43: Concatenate the 3-part name into one field
A44: dateOfBirth | B44: omit | D44: payer.personalInfo.dateOfBirth | E44: Date of birth | F44: Field | G44: Map | H44: CustomerCreditTransferInitiation.PaymentInformation.Debtor.Identification.PrivateIdentification.DateAndPlaceOfBirth.Birthdate | J44: https://www.iso20022.org/standardsrepository/type/DateAndPlaceOfBirth1 | K44: Format date into ISODate format
A45: amountType | B45: SEND | D45: amountType | E45: This element contains the amount type. Allowed values are: SEND (The amount the Payer would like to send, that is, the amount that should be withdrawn from the Payer account including any fees.) or RECEIVE (The amount the Payer would like the Payee to receive, that is, the amount that should be sent to the receiver exclusive fees.) | F45: Field | G45: Discard | K45: This field controls the disposition of the fee in relation to the transaction amount.
A46: amount | D46: amount | E46: Depending on amountType: If SEND: The amount the Payer would like to send, that is, the amount that should be withdrawn from the Payer account including any fees. The amount is updated by each participating entity in the transaction. If RECEIVE: The amount the Payee should receive, that is, the amount that should be sent to the receiver exclusive any fees. The amount is not updated by any of the participating entities. | F46: Collection
A47: currency | D47: amount.currency | E47: The currency of the amount. | F47: Field | G47: Map | H47: CustomerCreditTransferInitiation.PaymentInformation.CreditTransferTransaction.Amount.EquivalentAmount.CurrencyOfTransfer | J47: https://www.iso20022.org/standardsrepository/type/EquivalentAmount2 | K47: The currency in ISO20022 is supposed to be in the destination account currency, not the source account currency; however forex is not yet completely implemented in Mojaloop. We'll work around this for now.
A48: amount | D48: amount.amount | E48: The value of the amount of money. | F48: Field | G48: Map | H48: CustomerCreditTransferInitiation.PaymentInformation.CreditTransferTransaction.Amount.EquivalentAmount.Amount | J48: https://www.iso20022.org/standardsrepository/type/EquivalentAmount2
A49: fees | B49: omit | D49: fees | E49: The fees in the transaction. | F49: Collection
A50: currency | B50: omit | D50: fees.currency | E50: The currency of the fees amount. | F50: Field | G50: Map | H50: CustomerCreditTransferInitiation.PaymentInformation.CreditTransferTransaction.SupplementaryData | J50: https://www.iso20022.org/standardsrepository/type/CreditTransferTransaction40 | K50: There is no field for fees/charges in this message
A51: amount | B51: omit | D51: fees.amount | E51: The value of the fees amount | F51: Field | G51: Map | H51: CustomerCreditTransferInitiation.PaymentInformation.CreditTransferTransaction.SupplementaryData | J51: https://www.iso20022.org/standardsrepository/type/CreditTransferTransaction40 | K51: There is no field for fees/charges in this message
A52: transactionType | D52: transactionType | E52: The type of transaction that the quote is requested for. | F52: Collection
A53: scenario | B53: TRANSFER | D53: transactionType.scenario | E53: The nature of the transaction that the quote is requested for | F53: Field | G53: Map | H53: CustomerCreditTransferInitiation.PaymentInformation.CreditTransferTransaction.PaymentTypeInformation.CategoryPurpose.Proprietary | J53: https://www.iso20022.org/standardsrepository/type/CategoryPurpose1Choice
A54: subScenario | B54: omit | D54: transactionType.subScenario | E54: Possible sub-scenario, defined locally within the scheme. | F54: Field | G54: Discard
A55: initiator | B55: PAYER | D55: transactionType.initiator | E55: Who is initiating the transaction: payer or payee | F55: Field | G55: Map | H55: CustomerCreditTransferInitiation.GroupHeader.InitiatingParty.Identification.ContactDetails.MobileNumber | J55: https://www.iso20022.org/standardsrepository/type/Contact4 | K55: This should be the Payer MSISDN
A56: initiatorType | B56: CONSUMER | D56: transactionType.initiatorType | E56: The type of party initiating the transaction that the quote is requested for | F56: Field | G56: Map | H56: CustomerCreditTransferInitiation.SupplementaryData | J56: https://www.iso20022.org/standardsrepository/type/CustomerCreditTransferInitiationV10
A57: refundInfo | B57: omit | D57: transactionType.refundInfo | E57: Extra information specific to a refund scenario. Should only be populated if scenario is REFUND. | F57: Collection
A58: originalTransactionId | B58: omit | D58: transactionType.refundInfo.originalTransactionId | E58: Reference to the original transaction ID that is requested to be refunded. | F58: Field | G58: Discard
A59: refundReason | B59: omit | D59: transactionType.refundInfo.refundReason | E59: Free text indicating the reason for the refund. | F59: Field | G59: Discard
A60: balanceOfPayments | B60: omit | D60: transactionType.balanceOfPayments | E60: Balance of Payments code. | F60: Field | G60: Map | H60: CustomerCreditTransferInitiation.PaymentInformation.CreditTransferTransaction.RegulatoryReporting.* | J60: https://www.iso20022.org/standardsrepository/type/RegulatoryReporting3 | K60: This field contains several sub-fields that may have to be populated.
A61: geoCode | B61: omit | D61: geoCode | E61: Longitude and Latitude of the initiating Party. Can be used to detect fraud. | F61: Collection
A62: latitude | B62: omit | D62: geoCode.latitude | E62: The Latitude of the service initiating Party. | F62: Field | G62: Map | H62: CustomerCreditTransferInitiation.SupplementaryData | J62: https://www.iso20022.org/standardsrepository/type/CustomerCreditTransferInitiationV10
A63: longitude | B63: omit | D63: geoCode.longitude | E63: The Longitude of the service initiating Party. | F63: Field | G63: Map | H63: CustomerCreditTransferInitiation.SupplementaryData | J63: https://www.iso20022.org/standardsrepository/type/CustomerCreditTransferInitiationV10
A64: note | B64: omit | D64: note | E64: A memo that will be attached to the transaction. | F64: Field | G64: Map | H64: CustomerCreditTransferInitiation.PaymentInformation.CreditTransferTransaction.RemittanceInformation | J64: https://www.iso20022.org/standardsrepository/type/CreditTransferTransaction40
A65: expiration | D65: expiration | E65: Expiration is optional. It can be set to get a quick failure in case the peer FSP takes too long to respond. Also, it may be beneficial for Consumer, Agent, and Merchant to know that their request has a time limit. | F65: Field | G65: Discard
A66: extensionList | B66: omit | D66: extensionList | E66: Optional list of extensions to the quote or transfer, specific to deployment. | F66: Collection
A67: extension | D67: extensionList.extension | E67: An optional extension element defined by a key-value pair | F67: Collection
A68: key | D68: extensionList.extension.key | E68: The key for an optional extension element value | F68: Field | G68: Discard
A69: value | D69: extensionList.extension.value | E69: The value for an optional extension element key | F69: Field | G69: Discard

Sheet PUT quotes
A1: Mapping Mojaloop's PUT /quotes message onto ISO 20022 pain.013
A3: This mapping describes how the data elements of the Mojaloop PUT /quotes message (shown in column C) can be mapped onto the data elements of an outgoing pain.013 message (shown in column A). Where default values are to be applied, they are shown in Column B. This mapping assumes that only phone numbers will be used as identifiers.
A5: ISO pain.013 | B5: Default | C5: Moja | D5: Comment
A6: Document
A7: Document.CdtrPmtActvtnReq
A8: Document.CdtrPmtActvtnReq.GrpHdr
A9: Document.CdtrPmtActvtnReq.GrpHdr.MsgId | B9: Generate UUID
A10: Document.CdtrPmtActvtnReq.GrpHdr.CreDtTm | B10: Auto-generate NOW()
A11: Document.CdtrPmtActvtnReq.GrpHdr.NbOfTxs | B11: 1
A12: Document.CdtrPmtActvtnReq.GrpHdr.InitgPty
A13: Document.CdtrPmtActvtnReq.GrpHdr.InitgPty.Id
A14: Document.CdtrPmtActvtnReq.GrpHdr.InitgPty.Id.AnyBIC
A15: Document.CdtrPmtActvtnReq.PmtInf
A16: Document.CdtrPmtActvtnReq.PmtInf.PmtInfId | C16: Quote ID from the URI
A17: Document.CdtrPmtActvtnReq.PmtInf.PmtMtd | B17: TRF
A18: Document.CdtrPmtActvtnReq.PmtInf.ReqdExctnDt | B18: Today's date as YYYY-MM-DD
A19: Document.CdtrPmtActvtnReq.PmtInf.SvcLvl
A20: Document.CdtrPmtActvtnReq.PmtInf.SvcLvl.Cd | B20: SDVA
A21: Document.CdtrPmtActvtnReq.PmtInf.Dbtr
A22: Document.CdtrPmtActvtnReq.PmtInf.Dbtr.CtctDtls
A23: Document.CdtrPmtActvtnReq.PmtInf.Dbtr.CtctDtls.MobNb | C23: transaction.payer.partyIdInfo.partyIdentifier | D23: The Transaction object is in the ILP packet in encoded form
A24: Document.CdtrPmtActvtnReq.PmtInf.DbtrAgt
A25: Document.CdtrPmtActvtnReq.PmtInf.DbtrAgt.FinInstnId
A26: Document.CdtrPmtActvtnReq.PmtInf.DbtrAgt.FinInstnId.BICFI | C26: transaction.payer.fspId | D26: The Transaction object is in the ILP packet in encoded form
A27: Document.CdtrPmtActvtnReq.PmtInf.ChrgBr | B27: DEBT
A28: Document.CdtrPmtActvtnReq.PmtInf.Cndtn.Condition | C28: condition
A29: Document.CdtrPmtActvtnReq.PmtInf.CdtTrfTxInf
A30: Document.CdtrPmtActvtnReq.PmtInf.CdtTrfTxInf.PmtId | C30: transaction.transactionId
A31: Document.CdtrPmtActvtnReq.PmtInf.CdtTrfTxInf.Amt | C31: transferAmount.currency | D31: This goes in the Ccy attribute of the element.
A32: Document.CdtrPmtActvtnReq.PmtInf.CdtTrfTxInf.Amt | C32: transferAmount.Amount
A33: Document.CdtrPmtActvtnReq.PmtInf.CdtTrfTxInf.CdtrAgt
A34: Document.CdtrPmtActvtnReq.PmtInf.CdtTrfTxInf.CdtrAgt.FinInstnId
A35: Document.CdtrPmtActvtnReq.PmtInf.CdtTrfTxInf.CdtrAgt.FinInstnId.BICFI | C35: transaction.payee.fspId | D35: The Transaction object is in the ILP packet in encoded form
A36: Document.CdtrPmtActvtnReq.PmtInf.CdtTrfTxInf.Cdtr
A37: Document.CdtrPmtActvtnReq.PmtInf.CdtTrfTxInf.Cdtr.CtctDtls
A38: Document.CdtrPmtActvtnReq.PmtInf.CdtTrfTxInf.Cdtr.CtctDtls.Nm | C38: transaction.payee.name
A39: Document.CdtrPmtActvtnReq.PmtInf.CdtTrfTxInf.Cdtr.CtctDtls.MobNb | C39: transaction.payee.partyIdInfo.partyIdentifier | D39: The Transaction object is in the ILP packet in encoded form

Sheet POST transfers
A1: Mapping Mojaloop's POST /transfers message onto ISO 20022 pacs.008
A3: This mapping describes how an incoming pacs.008 message (shown in column C) can be mapped onto the data elements of the Mojaloop POST /transfers message (shown in column A). Where default values are to be applied, they are shown in Column B. This mapping assumes that only phone numbers will be used as identifiers.
A5: Moja | B5: Default | C5: ISO pacs.008 | D5: Comment
A6: transactionId | C6: Document.FIToFICstmrCdtTrf.CdtTrfTxInf.PmtId.EndToEndId | D6: How to pick up the transaction ID
A7: transferId | C7: Document.FIToFICstmrCdtTrf.CdtTrfTxInf.PmtId.InstrId
A8: payeeFsp | C8: Document.FIToFICstmrCdtTrf.CdtTrfTxInf.CdtrAgt.FinInstnId.BICFI
A9: payerFsp | C9: Document.FIToFICstmrCdtTrf.CdtTrfTxInf.DbtrAgt.FinInstnId.BICFI
A10: amount
A11: currency | C11: Document.FIToFICstmrCdtTrf.CdtTrfTxInf.IntrBkSttlmAmt | D11: Currency is in the Ccy attribute of this item
A12: amount | C12: Document.FIToFICstmrCdtTrf.CdtTrfTxInf.IntrBkSttlmAmt
A13: ilpPacket | D13: Pick this up from the PUT /quotes body…
A14: condition | C14: Document.FIToFICstmrCdtTrf.CdtTrfTxInf.Cndtn.Condition
A15: expiration | B15: We can construct this ourselves…
A16: extensionList | B16: omit

Sheet PUT transfers
A1: Mapping Mojaloop's PUT /transfers message onto ISO 20022 pacs.002
A3: This mapping describes how the data elements of the Mojaloop PUT /transfer message (shown in column C) can be mapped onto the data elements of an outgoing pacs.002 message (shown in column A). Where default values are to be applied, they are shown in Column B. This mapping assumes that only phone numbers will be used as identifiers.
A5: ISO pain.002 | B5: Default | C5: Moja | D5: Comment
A6: Document
A7: Document.FIToFIPmtStsRpt
A8: Document.FIToFIPmtStsRpt.GrpHdr
A9: Document.FIToFIPmtStsRpt.GrpHdr.MsgId | B9: Generate UUID
A10: Document.FIToFIPmtStsRpt.GrpHdr.CreDtTm | B10: Auto-generate NOW()
A11: Document.FIToFIPmtStsRpt.GrpHdr.IlpData
A12: Document.FIToFIPmtStsRpt.GrpHdr.IlpData.Fulfilment | C12: fulfilment | D12: Don't need to worry about this
A13: Document.FIToFIPmtStsRpt.GrpHdr.DbtrAgent
A14: Document.FIToFIPmtStsRpt.GrpHdr.DbtrAgt
A15: Document.FIToFIPmtStsRpt.GrpHdr.DbtrAgt.FininstnId
A16: Document.FIToFIPmtStsRpt.GrpHdr.DbtrAgt.FininstnId.BICFI | C16: transaction.payer.fspId | D16: This kind of assumes we're using BICs to identify participants - need to check this with RSwitch
A17: Document.FIToFIPmtStsRpt.GrpHdr.CdtrAgt
A18: Document.FIToFIPmtStsRpt.GrpHdr.CdtrAgt.FininstnId
A19: Document.FIToFIPmtStsRpt.GrpHdr.CdtrAgt.FininstnId.BICFI | C19: transaction.payee.fspId | D19: This kind of assumes we're using BICs to identify participants - need to check this with RSwitch
A20: Document.FIToFIPmtStsRpt.OrgnlGrpInfAndSts
A21: Document.FIToFIPmtStsRpt.OrgnlGrpInfAndSts.OrgnlMsgId | C21: transaction.transactionId
A22: Document.FIToFIPmtStsRpt.OrgnlGrpInfAndSts.OrgnlMsgNmId | B22: pacs.008.001.09
A23: Document.FIToFIPmtStsRpt.OrgnlGrpInfAndSts.GrpSts | B23: ACCC | D23: Assuming this was successful…

Sheet TransactionInitiatorType
A1: CONSUMER | B1: Consumer is the initiator of the transaction.
A2: AGENT | B2: Agent is the initiator of the transaction.
A3: BUSINESS | B3: Business is the initiator of the transaction.
A4: DEVICE | B4: Device is the initiator of the transaction.

Sheet TransactionInitiator
A1: PAYER | B1: The sender of funds is initiating the transaction. The account to send from is either owned by the Payer or is connected to the Payer in some way.
A2: PAYEE | B2: The recipient of the funds is also initiating the transaction by sending a transaction request. The Payer must approve the transaction, either automatically by a pre-generated OTP, pre-approval of the Payee, or by manually approving in his or her own Device.

Sheet TransactionScenario
A1: DEPOSIT | B1: Used for performing a Cash-In (deposit) transaction, where in the normal case electronic funds are transferred from a Business account to a Consumer account, and physical cash is given from the Consumer to the Business User.
A2: WITHDRAWAL | B2: Used for performing a Cash-Out (withdrawal) transaction, where in the normal case electronic funds are transferred from a Consumer’s account to a Business account, and physical cash is given from the Business User to the Consumer.
A3: TRANSFER | B3: Used for performing a P2P (Peer to Peer, or Consumer to Consumer) transaction.
A4: PAYMENT | B4: Typically used for performing a transaction from a Consumer to a Merchant/Organization, but could also be for a B2B (Business to Business) payment. The transaction could be online to purchase in an Internet store, in a physical store where both the Consumer and Business User are present, a bill payment, a donation, and so on.
A5: REFUND | B5: Used for performing a refund of transaction.

Sheet PartyIdType
A1: MSISDN | B1: Used when an MSISDN (Mobile Station International Subscriber Directory Number, that is, the phone number) is used as reference to a participant. The MSISDN identifier should be in international format according to the ITU-T E.164 standard. Optionally, the MSISDN may be prefixed by a single plus sign, indicating the international prefix.
A2: EMAIL | B2: Used when an email should be used as reference to a participant. The format of the email should be according to the informational RFC 3696.
A3: PERSONAL_ID | B3: Used when some kind of personal identifier should be used as reference to a participant. Examples of personal identification can be passport number, birth certificate number, national registration number or similar. The identifier number shall be added in the PartyIdentifier element. The personal identifier type shall be added in the PartySubIdOrType element.
A4: BUSINESS | B4: Used when a specific Business (for example, an Organization or a Company) should be used as reference to a participant. The Business identifier can be in any format. To make a transaction connected to a specific username or bill number in a Business, the PartySubIdOrType element should be used.
A5: DEVICE | B5: Used when a specific Device (for example, a POS or ATM) ID connected to a specific Business or Organization should be used as reference to a Party. To use a specific device under a specific Business or Organization, the PartySubIdOrType element should be used.
A6: ACCOUNT_ID | B6: Used when a bank account number or FSP account ID should be used as reference to a participant. The ACCOUNT_ID identifier can be in any format, as formats can greatly differ depending on country and FSP.
A7: IBAN | B7: Used when a bank account number or FSP account ID should be used as reference to a participant. The IBAN identifier can consist of up to 34 alphanumeric characters and should be entered without any whitespace.
A8: ALIAS | B8: Used when an alias should be used as reference to a participant. The alias should be created in the FSP as an alternative reference to an account owner. Another example of an alias can be username in the FSP system. The ALIAS identifier can be in any format. It is also possible to use the PartySubIdOrType element for identifying an account under an Alias defined by the PartyIdentifier.

Sheet PersonalIdentifierType
A1: PASSPORT | B1: Used when a passport number should be used as reference to a Party
A2: NATIONAL_REGISTRATION | B2: Used when a national registration number should be used as reference to a Party
A3: DRIVING_LICENSE | B3: Used when a driving license should be used as reference to a Party
A4: ALIEN_REGISTRATION | B4: Used when an alien registration number should be used as reference to a Party
A5: NATIONAL_ID_CARD | B5: Used when a national ID card number should be used as reference to a Party
A6: EMPLOYER_ID | B6: Used when a tax identification number should be used as reference to a Party
A7: TAXI_ID_NUMBER | B7: Used when a tax identification number should be used as reference to a Party.
A8: SENIOR_CITIZENS_CARD | B8: Used when a senior citizens card number should be used as reference to a Party
A9: MARRIAGE_CERTIFICATE | B9: Used when a marriage certificate number should be used as reference to a Party
A10: HEALTH_CARD | B10: Used when a health card number should be used as reference to a Party
A11: VOTERS_ID | B11: Used when a voters identification number should be used as reference to a Party
A12: UNITED_NATIONS | B12: Used when an UN (United Nations) number should be used as reference to a Party
A13: OTHER_ID | B13: Used when any other type of identification type number should be used as reference to a Party

Sheet TransferState
A1: RECEIVED | B1: Next ledger has received the transfer.
A2: RESERVED | B2: Next ledger has reserved the transfer.
A3: COMMITTED | B3: Next ledger has successfully performed the transfer.
A4: ABORTED | B4: Next ledger has aborted the transfer due a rejection or failure to perform the transfer.
